<?xml version="1.0" encoding="UTF-8"?>
<model xmlns="http://www.opengroup.org/xsd/archimate/3.0/" xmlns:xsi="http://www.w3.org/2001/XMLSchema-instance" xsi:schemaLocation="http://www.opengroup.org/xsd/archimate/3.0/ http://www.opengroup.org/xsd/archimate/3.1/archimate3_Diagram.xsd" identifier="id-9bbd7fb2">
  <name xml:lang="en">app example 3 (REST)</name>
  <elements>
    <element identifier="id-2272b3bb" xsi:type="ApplicationInterface">
      <name xml:lang="en">IFollowerDirectory</name>
    </element>
    <element identifier="id-461a15da" xsi:type="ApplicationProcess">
      <name xml:lang="en">List&lt;Follower&gt; FindUsersFollowers (string accountId)</name>
    </element>
    <element identifier="id-0c055819" xsi:type="ApplicationComponent">
      <name xml:lang="en">Follower</name>
    </element>
    <element identifier="c6eb43cd" xsi:type="DataObject">
      <name xml:lang="en">FollowerId</name>
    </element>
    <element identifier="id-75ac705b" xsi:type="DataObject">
      <name xml:lang="en">SocialTags[]</name>
    </element>
    <element identifier="b3fca1fb" xsi:type="DataObject">
      <name xml:lang="en">FollowerName</name>
    </element>
    <element identifier="e61924b1" xsi:type="ApplicationComponent">
      <name xml:lang="en">FollowerDirectory</name>
    </element>
    <element identifier="a910da7c" xsi:type="ApplicationProcess">
      <name xml:lang="en">List&lt;Follower&gt; FindUsersFollowers (string accountId)</name>
    </element>
    <element identifier="id-59cb2834" xsi:type="ApplicationComponent">
      <name xml:lang="en">EntryPointController</name>
    </element>
    <element identifier="id-4d2a8269" xsi:type="ApplicationFunction">
      <name xml:lang="en">EntryPointRepresentation Get() {HTTP GET}</name>
    </element>
    <element identifier="cdf2a8ee" xsi:type="ApplicationComponent">
      <name xml:lang="en">Follower</name>
    </element>
    <element identifier="f19bc08d" xsi:type="DataObject">
      <name xml:lang="en">FollowerId</name>
    </element>
    <element identifier="a5715b56" xsi:type="DataObject">
      <name xml:lang="en">SocialTags[]</name>
    </element>
    <element identifier="id-2a725037" xsi:type="DataObject">
      <name xml:lang="en">FollowerName</name>
    </element>
    <element identifier="c1158b79" xsi:type="ApplicationComponent">
      <name xml:lang="en">Recommender</name>
    </element>
    <element identifier="id-79d9d56b" xsi:type="ApplicationFunction">
      <name xml:lang="en">List&lt;string&gt; GetRecommendedUsers(string accountId)</name>
    </element>
    <element identifier="c23476b6" xsi:type="ApplicationInterface">
      <name xml:lang="en">IRecommender</name>
    </element>
    <element identifier="id-53bfacee" xsi:type="ApplicationFunction">
      <name xml:lang="en">List&lt;string&gt; GetRecommendedUsers(string accountId)</name>
    </element>
    <element identifier="id-1f988cf9" xsi:type="ApplicationComponent">
      <name xml:lang="en">Follower</name>
    </element>
    <element identifier="id-6256e972" xsi:type="DataObject">
      <name xml:lang="en">FollowerId</name>
    </element>
    <element identifier="id-1a91d3c9" xsi:type="DataObject">
      <name xml:lang="en">SocialTags[]</name>
    </element>
    <element identifier="fccbd006" xsi:type="DataObject">
      <name xml:lang="en">FollowerName</name>
    </element>
    <element identifier="id-1e84dc44" xsi:type="ApplicationComponent">
      <name xml:lang="en">FollowerDirectoryClient</name>
    </element>
    <element identifier="a9521761" xsi:type="ApplicationProcess">
      <name xml:lang="en">List&lt;Follower&gt; FindUsersFollowers (string accountId)</name>
    </element>
    <element identifier="id-05142199" xsi:type="ApplicationComponent">
      <name xml:lang="en">WebApiConfig</name>
    </element>
    <element identifier="d6efe369" xsi:type="ApplicationFunction">
      <name xml:lang="en">Register (HttpConfiguration config)</name>
    </element>
    <element identifier="a8ee8795" xsi:type="ApplicationProcess">
      <name xml:lang="en">/accountmanagement -&gt; EntryPointControler()</name>
    </element>
    <element identifier="aab2e980" xsi:type="ApplicationComponent">
      <name xml:lang="en">WebApiApplication</name>
    </element>
    <element identifier="id-28fe1ee0" xsi:type="ApplicationFunction">
      <name xml:lang="en">Application_Start()</name>
    </element>
    <element identifier="dac581b1" xsi:type="ApplicationProcess">
      <name xml:lang="en">set HAL-JSON as default</name>
    </element>
    <element identifier="d496da61" xsi:type="DataObject">
      <name xml:lang="en">EntryPointBaseUrl</name>
    </element>
    <element identifier="id-12f32271" xsi:type="DataObject">
      <name xml:lang="en">AccountsBaseUrl</name>
    </element>
    <element identifier="f1b548a3" xsi:type="ApplicationProcess">
      <name xml:lang="en">create JSON with links to entry points (accounts)</name>
    </element>
    <element identifier="id-44fcdd3d" xsi:type="ApplicationComponent">
      <name xml:lang="en">WebApiConfig</name>
    </element>
    <element identifier="id-9c970f90" xsi:type="ApplicationFunction">
      <name xml:lang="en">Register (HttpConfiguration config)</name>
    </element>
    <element identifier="ba0b2aa0" xsi:type="ApplicationProcess">
      <name xml:lang="en">/accountmanagement/accounts -&gt; AccountsControler.index()</name>
    </element>
    <element identifier="id-73f26451" xsi:type="ApplicationProcess">
      <name xml:lang="en">accountmanagement/accounts/{accountId} -&gt; AccountsControler.account()</name>
    </element>
    <element identifier="fe880ef5" xsi:type="ApplicationComponent">
      <name xml:lang="en">AccountsController</name>
    </element>
    <element identifier="id-2c9bd0fb" xsi:type="ApplicationFunction">
      <name xml:lang="en">AccountsRepresentation Index() {HTTP GET}</name>
    </element>
    <element identifier="a7f46b71" xsi:type="ApplicationProcess">
      <name xml:lang="en">create JSON with links to Accounts</name>
    </element>
    <element identifier="eb8e3d27" xsi:type="DataObject">
      <name xml:lang="en">EntryPointBaseUrl</name>
    </element>
    <element identifier="id-63f0fb70" xsi:type="DataObject">
      <name xml:lang="en">AccountsBaseUrl</name>
    </element>
    <element identifier="id-551786c2" xsi:type="ApplicationProcess">
      <name xml:lang="en">Enable CORS</name>
    </element>
    <element identifier="id-073974d0" xsi:type="ApplicationFunction">
      <name xml:lang="en">AccountsRepresentation Account (string accountId) {HTTP GET}</name>
    </element>
    <element identifier="c69d7259" xsi:type="ApplicationProcess">
      <name xml:lang="en">create JSON with links to AccountFollowersMenu for Account by ID</name>
    </element>
    <element identifier="b8fb79cf" xsi:type="ApplicationComponent">
      <name xml:lang="en">AccountRepresentation</name>
    </element>
    <element identifier="id-8d892a42" xsi:type="DataObject">
      <name xml:lang="en">AccountId</name>
    </element>
    <element identifier="f5027502" xsi:type="DataObject">
      <name xml:lang="en">Name</name>
    </element>
    <element identifier="id-32f7af32" xsi:type="ApplicationProcess">
      <name xml:lang="en">accountmanagement/accounts/{accountId}/followers -&gt; FollowersController.Index()</name>
    </element>
    <element identifier="id-149de91a" xsi:type="ApplicationComponent">
      <name xml:lang="en">FollowersController</name>
    </element>
    <element identifier="a7fa4d9f" xsi:type="DataObject">
      <name xml:lang="en">AccountsBaseUrl</name>
    </element>
    <element identifier="d2d5ff9b" xsi:type="ApplicationFunction">
      <name xml:lang="en">FollowersRepresentation Index (string accountId) {HTTP GET}</name>
    </element>
    <element identifier="id-75eaf240" xsi:type="ApplicationComponent">
      <name xml:lang="en">FollowersRepresentation</name>
    </element>
    <element identifier="id-764d4bcb" xsi:type="DataObject">
      <name xml:lang="en">followers[]</name>
    </element>
    <element identifier="id-49d7d048" xsi:type="DataObject">
      <name xml:lang="en">Name (copy)</name>
    </element>
    <element identifier="id-4c5a15e8" xsi:type="ApplicationProcess">
      <name xml:lang="en">create JSON with links to Followers</name>
    </element>
    <element identifier="id-42353705" xsi:type="ApplicationFunction">
      <name xml:lang="en">IndexPOST(string accountId, Follower follower)</name>
    </element>
    <element identifier="c3059711" xsi:type="ApplicationComponent">
      <name xml:lang="en">BeganFollowing</name>
    </element>
    <element identifier="id-0e0b4575" xsi:type="DataObject">
      <name xml:lang="en">AccountId</name>
    </element>
    <element identifier="id-37cc4cf0" xsi:type="DataObject">
      <name xml:lang="en">FollowerId</name>
    </element>
    <element identifier="id-1f3462e2" xsi:type="ApplicationProcess">
      <name xml:lang="en">sve to store</name>
    </element>
    <element identifier="id-75e6469b" xsi:type="ApplicationComponent">
      <name xml:lang="en">EventPersister</name>
    </element>
    <element identifier="id-4efb44bb" xsi:type="ApplicationFunction">
      <name xml:lang="en">PersistEvent(object ev)</name>
    </element>
    <element identifier="id-21fe1ef8" xsi:type="DataObject">
      <name xml:lang="en">config</name>
    </element>
    <element identifier="ac9ccc41" xsi:type="DataObject">
      <name xml:lang="en">accountmanagement/beganfollowing -&gt; BeganFollowingController.Feed()</name>
    </element>
    <element identifier="id-06235a52" xsi:type="ApplicationComponent">
      <name xml:lang="en">BeganFollowingController</name>
    </element>
    <element identifier="id-9ac9c23e" xsi:type="DataObject">
      <name xml:lang="en">BeganFollowingBaseUrl</name>
    </element>
    <element identifier="be4d1b24" xsi:type="ApplicationFunction">
      <name xml:lang="en">HttpResponseMessage Feed() {HTTP GET}</name>
    </element>
    <element identifier="d3693fe1" xsi:type="ApplicationProcess">
      <name xml:lang="en">get from store</name>
    </element>
    <element identifier="a33114ab" xsi:type="ApplicationComponent">
      <name xml:lang="en">EventRetriever</name>
    </element>
    <element identifier="id-45ca7810" xsi:type="ApplicationFunction">
      <name xml:lang="en">IEnumerable&lt;ResolvedEvent&gt; RecentEvents(string stream)</name>
    </element>
    <element identifier="id-9095d7ca" xsi:type="ApplicationProcess">
      <name xml:lang="en">create ATOM with feeds</name>
    </element>
    <element identifier="ca0a40a9" xsi:type="ApplicationComponent">
      <name xml:lang="en">BeganFollowingPollingFeedConsumer</name>
    </element>
    <element identifier="id-4c2c51ec" xsi:type="DataObject">
      <name xml:lang="en">EntryPointUrl</name>
    </element>
    <element identifier="cb05e122" xsi:type="DataObject">
      <name xml:lang="en">LastEventIdProcessed</name>
    </element>
    <element identifier="b93dd2ac" xsi:type="ApplicationFunction">
      <name xml:lang="en">Main()</name>
    </element>
    <element identifier="acdb4e5d" xsi:type="ApplicationProcess">
      <name xml:lang="en">infinite loop</name>
    </element>
    <element identifier="d4767110" xsi:type="ApplicationProcess">
      <name xml:lang="en">get unprocessed event</name>
    </element>
    <element identifier="id-9480a96a" xsi:type="ApplicationFunction">
      <name xml:lang="en">FetchFeed()</name>
    </element>
    <element identifier="e8f50ee1" xsi:type="ApplicationProcess">
      <name xml:lang="en">call account context</name>
    </element>
    <element identifier="id-20dcbb18" xsi:type="TechnologyFunction">
      <name xml:lang="en">Technology Function</name>
    </element>
    <element identifier="c325a498" xsi:type="TechnologyFunction">
      <name xml:lang="en">Technology Function</name>
    </element>
    <element identifier="id-5014ebdb" xsi:type="TechnologyFunction">
      <name xml:lang="en">Technology Function</name>
    </element>
    <element identifier="d0d4b84b" xsi:type="TechnologyService">
      <name xml:lang="en">network</name>
      <documentation xml:lang="en">Network errors have been such a major source of problems.&#xD;
&#xD;
 synchronous communication is a fundamental part of the problem.(тк юзер может не дождаться синхронного ответа, temporal coupling)&#xD;
&#xD;
распределенные транзакции: если мы блокируем одну систему и ждем доступность второй то первой системе накапливаются блокировки (что и оказывает влияние на масштабируемость и надежность)</documentation>
    </element>
    <element identifier="id-3d07a689" xsi:type="TechnologyFunction">
      <name xml:lang="en">event store</name>
    </element>
    <element identifier="id-3e1fe537" xsi:type="Grouping">
      <name xml:lang="en">account management</name>
    </element>
    <element identifier="id-037bfd41" xsi:type="Grouping">
      <name xml:lang="en">AccountManagement.Accounts. Api</name>
    </element>
    <element identifier="c2aa831d" xsi:type="Grouping">
      <name xml:lang="en">AccountManagement.EntryPoint.Api.Controllers</name>
    </element>
    <element identifier="id-46e885a0" xsi:type="Grouping">
      <name xml:lang="en">marketing</name>
    </element>
    <element identifier="bcc4903f" xsi:type="Grouping">
      <name xml:lang="en">User’s Homepage</name>
    </element>
    <element identifier="id-1e2e80cc" xsi:type="Grouping">
      <name xml:lang="en">Discovery</name>
    </element>
    <element identifier="id-821f3e6a" xsi:type="Grouping">
      <name xml:lang="en">Discovery.Recommendations.Followers</name>
    </element>
    <element identifier="f9b69534" xsi:type="Grouping">
      <name xml:lang="en">Discovery.Followers.BeganFollowingConsumer</name>
    </element>
    <element identifier="id-9fdc1d3c" xsi:type="Grouping">
      <name xml:lang="en">payment provider</name>
    </element>
    <element identifier="id-9e77e08a" xsi:type="Grouping">
      <name xml:lang="en">shipping provider</name>
    </element>
    <element identifier="b37b5820" xsi:type="Grouping">
      <name xml:lang="en">internet</name>
      <documentation xml:lang="en">a distributed system that has agents&#xD;
running on every component that sends or receives messages—avoiding the need for a centralized&#xD;
single point of failure.</documentation>
    </element>
    <element identifier="aee8a19e" xsi:type="Grouping">
      <name xml:lang="en">AccountManagement.EntryPoint.Api</name>
    </element>
    <element identifier="id-94446089" xsi:type="Grouping">
      <name xml:lang="en">AccountManagement.Accounts.Api.Controllers</name>
    </element>
    <element identifier="id-3f490911" xsi:type="Grouping">
      <name xml:lang="en">AccountManagement. RegularAccounts.BeganFollowing</name>
    </element>
  </elements>
  <relationships>
    <relationship identifier="fba59633" source="id-1e2e80cc" target="f9b69534" xsi:type="Composition" />
    <relationship identifier="db1330eb" source="id-20dcbb18" target="id-461a15da" xsi:type="Flow" />
    <relationship identifier="fed9aa12" source="id-821f3e6a" target="c23476b6" xsi:type="Composition" />
    <relationship identifier="id-3b90fcda" source="f9b69534" target="id-1e84dc44" xsi:type="Composition" />
    <relationship identifier="id-19952c51" source="c325a498" target="d0d4b84b" xsi:type="Association" />
    <relationship identifier="id-32bbb763" source="e61924b1" target="id-2272b3bb" xsi:type="Realization" />
    <relationship identifier="id-94805154" source="id-1f988cf9" target="id-1a91d3c9" xsi:type="Access" accessType="Write" />
    <relationship identifier="id-6c5ae185" source="cdf2a8ee" target="a5715b56" xsi:type="Access" accessType="Write" />
    <relationship identifier="id-02afbeb8" source="id-0c055819" target="b3fca1fb" xsi:type="Access" accessType="Write" />
    <relationship identifier="id-9bceea65" source="id-79d9d56b" target="a9521761" xsi:type="Flow" />
    <relationship identifier="id-19ee8e35" source="id-037bfd41" target="id-0c055819" xsi:type="Composition" />
    <relationship identifier="ae95f948" source="id-3e1fe537" target="c2aa831d" xsi:type="Composition" />
    <relationship identifier="id-8489923e" source="id-1e2e80cc" target="id-821f3e6a" xsi:type="Composition" />
    <relationship identifier="id-6387d726" source="id-1e2e80cc" target="id-5014ebdb" xsi:type="Composition" />
    <relationship identifier="id-0ec0b8d4" source="bcc4903f" target="c325a498" xsi:type="Composition" />
    <relationship identifier="e840b968" source="id-1f988cf9" target="fccbd006" xsi:type="Access" accessType="Write" />
    <relationship identifier="id-26fc568a" source="id-0c055819" target="db1330eb" xsi:type="Association" />
    <relationship identifier="af8a560a" source="id-1f988cf9" target="id-6256e972" xsi:type="Access" accessType="Write" />
    <relationship identifier="cd185f4e" source="id-037bfd41" target="e61924b1" xsi:type="Composition" />
    <relationship identifier="id-274dfdb0" source="id-0c055819" target="id-75ac705b" xsi:type="Access" accessType="Write" />
    <relationship identifier="bc599d4c" source="id-20dcbb18" target="d0d4b84b" xsi:type="Association" />
    <relationship identifier="id-366259d2" source="id-3e1fe537" target="id-20dcbb18" xsi:type="Composition" />
    <relationship identifier="id-4ef31a7c" source="c2aa831d" target="id-59cb2834" xsi:type="Composition" />
    <relationship identifier="id-01a8c3b0" source="id-1f988cf9" target="id-9bceea65" xsi:type="Association" />
    <relationship identifier="id-4cf71dc0" source="id-0c055819" target="id-1f988cf9" xsi:type="Association" />
    <relationship identifier="a0c4da51" source="cdf2a8ee" target="f19bc08d" xsi:type="Access" accessType="Write" />
    <relationship identifier="id-50d9c903" source="id-037bfd41" target="id-2272b3bb" xsi:type="Composition" />
    <relationship identifier="fd674009" source="cdf2a8ee" target="id-2a725037" xsi:type="Access" accessType="Write" />
    <relationship identifier="a3066079" source="f9b69534" target="id-1f988cf9" xsi:type="Composition" />
    <relationship identifier="id-528b9ba7" source="b37b5820" target="d0d4b84b" xsi:type="Composition" />
    <relationship identifier="c2b2eb5d" source="id-0c055819" target="c6eb43cd" xsi:type="Access" accessType="Write" />
    <relationship identifier="id-861e68b3" source="c1158b79" target="c23476b6" xsi:type="Realization" />
    <relationship identifier="id-1aa82c57" source="a9521761" target="id-5014ebdb" xsi:type="Flow" />
    <relationship identifier="id-955efd64" source="id-1e84dc44" target="a9521761" xsi:type="Assignment" />
    <relationship identifier="c69e68ff" source="e61924b1" target="a910da7c" xsi:type="Assignment" />
    <relationship identifier="id-6b6520c8" source="id-3e1fe537" target="id-037bfd41" xsi:type="Composition" />
    <relationship identifier="id-898841d9" source="id-59cb2834" target="id-4d2a8269" xsi:type="Assignment" />
    <relationship identifier="id-78588b88" source="c1158b79" target="id-79d9d56b" xsi:type="Assignment" />
    <relationship identifier="id-17e05c85" source="c2aa831d" target="cdf2a8ee" xsi:type="Composition" />
    <relationship identifier="id-40c070e0" source="id-821f3e6a" target="c1158b79" xsi:type="Composition" />
    <relationship identifier="id-0aa8d98c" source="id-5014ebdb" target="d0d4b84b" xsi:type="Association" />
    <relationship identifier="e442217d" source="id-3e1fe537" target="aee8a19e" xsi:type="Composition" />
    <relationship identifier="db6b53d8" source="aee8a19e" target="id-05142199" xsi:type="Composition" />
    <relationship identifier="e11c9bc3" source="id-05142199" target="d6efe369" xsi:type="Assignment" />
    <relationship identifier="id-96851528" source="d6efe369" target="a8ee8795" xsi:type="Composition" />
    <relationship identifier="a8c792ce" source="aee8a19e" target="aab2e980" xsi:type="Composition" />
    <relationship identifier="ceb62fc3" source="aab2e980" target="id-28fe1ee0" xsi:type="Assignment" />
    <relationship identifier="dc37bf4a" source="id-28fe1ee0" target="dac581b1" xsi:type="Composition" />
    <relationship identifier="a2169261" source="id-59cb2834" target="d496da61" xsi:type="Access" accessType="Write" />
    <relationship identifier="d2132295" source="id-59cb2834" target="id-12f32271" xsi:type="Access" accessType="Write" />
    <relationship identifier="bc4f9358" source="id-4d2a8269" target="f1b548a3" xsi:type="Composition" />
    <relationship identifier="id-21d9fd04" source="f1b548a3" target="d496da61" xsi:type="Access" accessType="Write" />
    <relationship identifier="id-559be726" source="f1b548a3" target="id-12f32271" xsi:type="Access" accessType="Write" />
    <relationship identifier="id-99a86104" source="id-20dcbb18" target="id-59cb2834" xsi:type="Flow" />
    <relationship identifier="b88f7353" source="id-44fcdd3d" target="id-9c970f90" xsi:type="Assignment" />
    <relationship identifier="id-483c0f06" source="id-9c970f90" target="ba0b2aa0" xsi:type="Composition" />
    <relationship identifier="b5ddfd9d" source="id-037bfd41" target="id-44fcdd3d" xsi:type="Composition" />
    <relationship identifier="bd577063" source="id-9c970f90" target="id-73f26451" xsi:type="Composition" />
    <relationship identifier="a827cad4" source="fe880ef5" target="id-63f0fb70" xsi:type="Access" accessType="Write" />
    <relationship identifier="id-4be83721" source="a7f46b71" target="id-63f0fb70" xsi:type="Access" accessType="Write" />
    <relationship identifier="id-25be6b04" source="id-94446089" target="fe880ef5" xsi:type="Composition" />
    <relationship identifier="id-60e15ff1" source="fe880ef5" target="eb8e3d27" xsi:type="Access" accessType="Write" />
    <relationship identifier="id-14ebad19" source="a7f46b71" target="eb8e3d27" xsi:type="Access" accessType="Write" />
    <relationship identifier="id-13e1b5b5" source="id-2c9bd0fb" target="a7f46b71" xsi:type="Composition" />
    <relationship identifier="c882700f" source="fe880ef5" target="id-2c9bd0fb" xsi:type="Assignment" />
    <relationship identifier="id-176c4bd5" source="id-3e1fe537" target="id-94446089" xsi:type="Composition" />
    <relationship identifier="id-883a9631" source="id-9c970f90" target="id-551786c2" xsi:type="Composition" />
    <relationship identifier="a56699d5" source="id-073974d0" target="c69d7259" xsi:type="Composition" />
    <relationship identifier="id-14a12da1" source="fe880ef5" target="id-073974d0" xsi:type="Assignment" />
    <relationship identifier="af661ec4" source="id-20dcbb18" target="id-073974d0" xsi:type="Flow" />
    <relationship identifier="id-59995056" source="id-3e1fe537" target="b8fb79cf" xsi:type="Composition" />
    <relationship identifier="be37e177" source="b8fb79cf" target="id-8d892a42" xsi:type="Access" accessType="Write" />
    <relationship identifier="id-91acb3cc" source="b8fb79cf" target="f5027502" xsi:type="Access" accessType="Write" />
    <relationship identifier="id-73d63986" source="af661ec4" target="b8fb79cf" xsi:type="Association" />
    <relationship identifier="a4d722a2" source="c69d7259" target="id-63f0fb70" xsi:type="Access" accessType="Write" />
    <relationship identifier="id-0a7447b7" source="id-9c970f90" target="id-32f7af32" xsi:type="Composition" />
    <relationship identifier="b92ec0a0" source="id-94446089" target="id-149de91a" xsi:type="Composition" />
    <relationship identifier="c88faa01" source="id-149de91a" target="a7fa4d9f" xsi:type="Access" accessType="Write" />
    <relationship identifier="id-07f862d1" source="id-149de91a" target="d2d5ff9b" xsi:type="Assignment" />
    <relationship identifier="id-04a3dac7" source="id-4c5a15e8" target="a7fa4d9f" xsi:type="Access" accessType="Write" />
    <relationship identifier="e2bf9ed4" source="id-3e1fe537" target="id-75eaf240" xsi:type="Composition" />
    <relationship identifier="id-8bb10ed1" source="id-75eaf240" target="id-764d4bcb" xsi:type="Access" accessType="Write" />
    <relationship identifier="id-981a0637" source="id-75eaf240" target="id-49d7d048" xsi:type="Access" accessType="Write" />
    <relationship identifier="id-8c441cb0" source="id-20dcbb18" target="id-2c9bd0fb" xsi:type="Flow" />
    <relationship identifier="id-2c47024d" source="id-20dcbb18" target="d2d5ff9b" xsi:type="Flow" />
    <relationship identifier="d1ac6f63" source="id-75eaf240" target="id-2c47024d" xsi:type="Association" />
    <relationship identifier="id-4509cf45" source="d2d5ff9b" target="id-4c5a15e8" xsi:type="Composition" />
    <relationship identifier="id-6fa999c8" source="id-149de91a" target="id-42353705" xsi:type="Assignment" />
    <relationship identifier="c2ff24a0" source="id-3e1fe537" target="c3059711" xsi:type="Composition" />
    <relationship identifier="id-559f57d1" source="c3059711" target="id-0e0b4575" xsi:type="Access" accessType="Write" />
    <relationship identifier="d7f96c48" source="c3059711" target="id-37cc4cf0" xsi:type="Access" accessType="Write" />
    <relationship identifier="id-9c61f705" source="id-3e1fe537" target="id-3d07a689" xsi:type="Composition" />
    <relationship identifier="a15e6928" source="id-42353705" target="id-1f3462e2" xsi:type="Composition" />
    <relationship identifier="id-4a7ad951" source="id-1f3462e2" target="id-4efb44bb" xsi:type="Flow" />
    <relationship identifier="f6afe33d" source="c3059711" target="id-4a7ad951" xsi:type="Association" />
    <relationship identifier="id-6f8bf964" source="id-3e1fe537" target="id-75e6469b" xsi:type="Composition" />
    <relationship identifier="ec14b974" source="id-75e6469b" target="id-4efb44bb" xsi:type="Assignment" />
    <relationship identifier="id-3701b1fa" source="id-75e6469b" target="id-3d07a689" xsi:type="Association" />
    <relationship identifier="id-38e94c01" source="id-20dcbb18" target="id-42353705" xsi:type="Flow" />
    <relationship identifier="d0027bbf" source="id-32f7af32" target="id-149de91a" xsi:type="Association" />
    <relationship identifier="id-63c9fb11" source="id-73f26451" target="id-073974d0" xsi:type="Association" />
    <relationship identifier="f49eba3b" source="ba0b2aa0" target="id-2c9bd0fb" xsi:type="Association" />
    <relationship identifier="fb6e111d" source="a8ee8795" target="id-4d2a8269" xsi:type="Association" />
    <relationship identifier="id-7b9d1ca5" source="id-3e1fe537" target="id-3f490911" xsi:type="Composition" />
    <relationship identifier="e605a21a" source="id-3f490911" target="id-21fe1ef8" xsi:type="Composition" />
    <relationship identifier="d00f2b3f" source="id-21fe1ef8" target="ac9ccc41" xsi:type="Composition" />
    <relationship identifier="id-92c4f48a" source="id-3f490911" target="id-06235a52" xsi:type="Composition" />
    <relationship identifier="fd4738b4" source="id-06235a52" target="id-9ac9c23e" xsi:type="Access" accessType="Write" />
    <relationship identifier="id-20d27c0a" source="id-06235a52" target="be4d1b24" xsi:type="Assignment" />
    <relationship identifier="b053624e" source="be4d1b24" target="d3693fe1" xsi:type="Composition" />
    <relationship identifier="id-145233b7" source="id-3e1fe537" target="a33114ab" xsi:type="Composition" />
    <relationship identifier="id-7397ca2a" source="a33114ab" target="id-45ca7810" xsi:type="Assignment" />
    <relationship identifier="id-6be3a7db" source="d3693fe1" target="id-45ca7810" xsi:type="Flow" />
    <relationship identifier="id-5cea3d2c" source="a33114ab" target="id-3d07a689" xsi:type="Association" />
    <relationship identifier="id-6f1c36dc" source="be4d1b24" target="id-9095d7ca" xsi:type="Composition" />
    <relationship identifier="id-6f4563da" source="id-9095d7ca" target="id-9ac9c23e" xsi:type="Access" accessType="Write" />
    <relationship identifier="fc4029e2" source="ac9ccc41" target="be4d1b24" xsi:type="Association" />
    <relationship identifier="id-7816d6d1" source="f9b69534" target="ca0a40a9" xsi:type="Composition" />
    <relationship identifier="id-1fd2d9fa" source="ca0a40a9" target="id-4c2c51ec" xsi:type="Access" accessType="Write" />
    <relationship identifier="id-0a4743ff" source="ca0a40a9" target="cb05e122" xsi:type="Access" accessType="Write" />
    <relationship identifier="cdb532e7" source="ca0a40a9" target="b93dd2ac" xsi:type="Assignment" />
    <relationship identifier="id-1d2e8f2c" source="b93dd2ac" target="acdb4e5d" xsi:type="Composition" />
    <relationship identifier="bc1fb16c" source="acdb4e5d" target="d4767110" xsi:type="Composition" />
    <relationship identifier="id-9a96cf7c" source="ca0a40a9" target="id-9480a96a" xsi:type="Assignment" />
    <relationship identifier="id-6e6f07b6" source="id-9480a96a" target="id-4c2c51ec" xsi:type="Access" accessType="Write" />
    <relationship identifier="c7546626" source="d4767110" target="id-9480a96a" xsi:type="Flow" />
    <relationship identifier="fa68cb78" source="id-9480a96a" target="e8f50ee1" xsi:type="Composition" />
    <relationship identifier="id-2867a96f" source="e8f50ee1" target="id-5014ebdb" xsi:type="Flow" />
  </relationships>
  <organizations>
    <item>
      <label xml:lang="en">Application</label>
      <item identifierRef="id-2272b3bb" />
      <item identifierRef="id-461a15da" />
      <item identifierRef="id-0c055819" />
      <item identifierRef="c6eb43cd" />
      <item identifierRef="id-75ac705b" />
      <item identifierRef="b3fca1fb" />
      <item identifierRef="e61924b1" />
      <item identifierRef="a910da7c" />
      <item identifierRef="id-59cb2834" />
      <item identifierRef="id-4d2a8269" />
      <item identifierRef="cdf2a8ee" />
      <item identifierRef="f19bc08d" />
      <item identifierRef="a5715b56" />
      <item identifierRef="id-2a725037" />
      <item identifierRef="c1158b79" />
      <item identifierRef="id-79d9d56b" />
      <item identifierRef="c23476b6" />
      <item identifierRef="id-53bfacee" />
      <item identifierRef="id-1f988cf9" />
      <item identifierRef="id-6256e972" />
      <item identifierRef="id-1a91d3c9" />
      <item identifierRef="fccbd006" />
      <item identifierRef="id-1e84dc44" />
      <item identifierRef="a9521761" />
      <item identifierRef="id-05142199" />
      <item identifierRef="d6efe369" />
      <item identifierRef="a8ee8795" />
      <item identifierRef="aab2e980" />
      <item identifierRef="id-28fe1ee0" />
      <item identifierRef="dac581b1" />
      <item identifierRef="d496da61" />
      <item identifierRef="id-12f32271" />
      <item identifierRef="f1b548a3" />
      <item identifierRef="id-44fcdd3d" />
      <item identifierRef="id-9c970f90" />
      <item identifierRef="ba0b2aa0" />
      <item identifierRef="id-73f26451" />
      <item identifierRef="fe880ef5" />
      <item identifierRef="id-2c9bd0fb" />
      <item identifierRef="a7f46b71" />
      <item identifierRef="eb8e3d27" />
      <item identifierRef="id-63f0fb70" />
      <item identifierRef="id-551786c2" />
      <item identifierRef="id-073974d0" />
      <item identifierRef="c69d7259" />
      <item identifierRef="b8fb79cf" />
      <item identifierRef="id-8d892a42" />
      <item identifierRef="f5027502" />
      <item identifierRef="id-32f7af32" />
      <item identifierRef="id-149de91a" />
      <item identifierRef="a7fa4d9f" />
      <item identifierRef="d2d5ff9b" />
      <item identifierRef="id-75eaf240" />
      <item identifierRef="id-764d4bcb" />
      <item identifierRef="id-49d7d048" />
      <item identifierRef="id-4c5a15e8" />
      <item identifierRef="id-42353705" />
      <item identifierRef="c3059711" />
      <item identifierRef="id-0e0b4575" />
      <item identifierRef="id-37cc4cf0" />
      <item identifierRef="id-1f3462e2" />
      <item identifierRef="id-75e6469b" />
      <item identifierRef="id-4efb44bb" />
      <item identifierRef="id-21fe1ef8" />
      <item identifierRef="ac9ccc41" />
      <item identifierRef="id-06235a52" />
      <item identifierRef="id-9ac9c23e" />
      <item identifierRef="be4d1b24" />
      <item identifierRef="d3693fe1" />
      <item identifierRef="a33114ab" />
      <item identifierRef="id-45ca7810" />
      <item identifierRef="id-9095d7ca" />
      <item identifierRef="ca0a40a9" />
      <item identifierRef="id-4c2c51ec" />
      <item identifierRef="cb05e122" />
      <item identifierRef="b93dd2ac" />
      <item identifierRef="acdb4e5d" />
      <item identifierRef="d4767110" />
      <item identifierRef="id-9480a96a" />
      <item identifierRef="e8f50ee1" />
    </item>
    <item>
      <label xml:lang="en">Technology &amp; Physical</label>
      <item identifierRef="id-20dcbb18" />
      <item identifierRef="c325a498" />
      <item identifierRef="id-5014ebdb" />
      <item identifierRef="d0d4b84b" />
      <item identifierRef="id-3d07a689" />
    </item>
    <item>
      <label xml:lang="en">Other</label>
      <item identifierRef="id-3e1fe537" />
      <item identifierRef="id-037bfd41" />
      <item identifierRef="c2aa831d" />
      <item identifierRef="id-46e885a0" />
      <item identifierRef="bcc4903f" />
      <item identifierRef="id-1e2e80cc" />
      <item identifierRef="id-821f3e6a" />
      <item identifierRef="f9b69534" />
      <item identifierRef="id-9fdc1d3c" />
      <item identifierRef="id-9e77e08a" />
      <item identifierRef="b37b5820" />
      <item identifierRef="aee8a19e" />
      <item identifierRef="id-94446089" />
      <item identifierRef="id-3f490911" />
    </item>
    <item>
      <label xml:lang="en">Relations</label>
      <item identifierRef="fba59633" />
      <item identifierRef="db1330eb" />
      <item identifierRef="fed9aa12" />
      <item identifierRef="id-3b90fcda" />
      <item identifierRef="id-19952c51" />
      <item identifierRef="id-32bbb763" />
      <item identifierRef="id-94805154" />
      <item identifierRef="id-6c5ae185" />
      <item identifierRef="id-02afbeb8" />
      <item identifierRef="id-9bceea65" />
      <item identifierRef="id-19ee8e35" />
      <item identifierRef="ae95f948" />
      <item identifierRef="id-8489923e" />
      <item identifierRef="id-6387d726" />
      <item identifierRef="id-0ec0b8d4" />
      <item identifierRef="e840b968" />
      <item identifierRef="id-26fc568a" />
      <item identifierRef="af8a560a" />
      <item identifierRef="cd185f4e" />
      <item identifierRef="id-274dfdb0" />
      <item identifierRef="bc599d4c" />
      <item identifierRef="id-366259d2" />
      <item identifierRef="id-4ef31a7c" />
      <item identifierRef="id-01a8c3b0" />
      <item identifierRef="id-4cf71dc0" />
      <item identifierRef="a0c4da51" />
      <item identifierRef="id-50d9c903" />
      <item identifierRef="fd674009" />
      <item identifierRef="a3066079" />
      <item identifierRef="id-528b9ba7" />
      <item identifierRef="c2b2eb5d" />
      <item identifierRef="id-861e68b3" />
      <item identifierRef="id-1aa82c57" />
      <item identifierRef="id-955efd64" />
      <item identifierRef="c69e68ff" />
      <item identifierRef="id-6b6520c8" />
      <item identifierRef="id-898841d9" />
      <item identifierRef="id-78588b88" />
      <item identifierRef="id-17e05c85" />
      <item identifierRef="id-40c070e0" />
      <item identifierRef="id-0aa8d98c" />
      <item identifierRef="e442217d" />
      <item identifierRef="db6b53d8" />
      <item identifierRef="e11c9bc3" />
      <item identifierRef="id-96851528" />
      <item identifierRef="a8c792ce" />
      <item identifierRef="ceb62fc3" />
      <item identifierRef="dc37bf4a" />
      <item identifierRef="a2169261" />
      <item identifierRef="d2132295" />
      <item identifierRef="bc4f9358" />
      <item identifierRef="id-21d9fd04" />
      <item identifierRef="id-559be726" />
      <item identifierRef="id-99a86104" />
      <item identifierRef="b88f7353" />
      <item identifierRef="id-483c0f06" />
      <item identifierRef="b5ddfd9d" />
      <item identifierRef="bd577063" />
      <item identifierRef="a827cad4" />
      <item identifierRef="id-4be83721" />
      <item identifierRef="id-25be6b04" />
      <item identifierRef="id-60e15ff1" />
      <item identifierRef="id-14ebad19" />
      <item identifierRef="id-13e1b5b5" />
      <item identifierRef="c882700f" />
      <item identifierRef="id-176c4bd5" />
      <item identifierRef="id-883a9631" />
      <item identifierRef="a56699d5" />
      <item identifierRef="id-14a12da1" />
      <item identifierRef="af661ec4" />
      <item identifierRef="id-59995056" />
      <item identifierRef="be37e177" />
      <item identifierRef="id-91acb3cc" />
      <item identifierRef="id-73d63986" />
      <item identifierRef="a4d722a2" />
      <item identifierRef="id-0a7447b7" />
      <item identifierRef="b92ec0a0" />
      <item identifierRef="c88faa01" />
      <item identifierRef="id-07f862d1" />
      <item identifierRef="id-04a3dac7" />
      <item identifierRef="e2bf9ed4" />
      <item identifierRef="id-8bb10ed1" />
      <item identifierRef="id-981a0637" />
      <item identifierRef="id-8c441cb0" />
      <item identifierRef="id-2c47024d" />
      <item identifierRef="d1ac6f63" />
      <item identifierRef="id-4509cf45" />
      <item identifierRef="id-6fa999c8" />
      <item identifierRef="c2ff24a0" />
      <item identifierRef="id-559f57d1" />
      <item identifierRef="d7f96c48" />
      <item identifierRef="id-9c61f705" />
      <item identifierRef="a15e6928" />
      <item identifierRef="id-4a7ad951" />
      <item identifierRef="f6afe33d" />
      <item identifierRef="id-6f8bf964" />
      <item identifierRef="ec14b974" />
      <item identifierRef="id-3701b1fa" />
      <item identifierRef="id-38e94c01" />
      <item identifierRef="d0027bbf" />
      <item identifierRef="id-63c9fb11" />
      <item identifierRef="f49eba3b" />
      <item identifierRef="fb6e111d" />
      <item identifierRef="id-7b9d1ca5" />
      <item identifierRef="e605a21a" />
      <item identifierRef="d00f2b3f" />
      <item identifierRef="id-92c4f48a" />
      <item identifierRef="fd4738b4" />
      <item identifierRef="id-20d27c0a" />
      <item identifierRef="b053624e" />
      <item identifierRef="id-145233b7" />
      <item identifierRef="id-7397ca2a" />
      <item identifierRef="id-6be3a7db" />
      <item identifierRef="id-5cea3d2c" />
      <item identifierRef="id-6f1c36dc" />
      <item identifierRef="id-6f4563da" />
      <item identifierRef="fc4029e2" />
      <item identifierRef="id-7816d6d1" />
      <item identifierRef="id-1fd2d9fa" />
      <item identifierRef="id-0a4743ff" />
      <item identifierRef="cdb532e7" />
      <item identifierRef="id-1d2e8f2c" />
      <item identifierRef="bc1fb16c" />
      <item identifierRef="id-9a96cf7c" />
      <item identifierRef="id-6e6f07b6" />
      <item identifierRef="c7546626" />
      <item identifierRef="fa68cb78" />
      <item identifierRef="id-2867a96f" />
    </item>
    <item>
      <label xml:lang="en">Views</label>
      <item identifierRef="d7b14242" />
    </item>
  </organizations>
  <views>
    <diagrams>
      <view identifier="d7b14242" xsi:type="Diagram">
        <name xml:lang="en">example</name>
        <node identifier="eb4cb296" xsi:type="Label" x="201" y="3246" w="6318" h="884">
          <label xml:lang="en">Application Services Layer (operational)</label>
          <style>
            <fillColor r="210" g="215" b="215" a="100" />
            <lineColor r="92" g="92" b="92" a="100" />
            <font name="Lucida Grande" size="12">
              <color r="0" g="0" b="0" />
            </font>
          </style>
        </node>
        <node identifier="c0650546" xsi:type="Label" x="201" y="2301" w="6318" h="884">
          <label xml:lang="en">Domain Layer (model)</label>
          <style>
            <fillColor r="184" g="192" b="192" a="100" />
            <lineColor r="92" g="92" b="92" a="100" />
            <font name="Lucida Grande" size="12">
              <color r="0" g="0" b="0" />
            </font>
          </style>
        </node>
        <node identifier="b724e541" xsi:type="Label" x="201" y="4186" w="6318" h="884">
          <label xml:lang="en">Infrаstrсtиrе Layer</label>
          <style>
            <fillColor r="210" g="215" b="215" a="100" />
            <lineColor r="92" g="92" b="92" a="100" />
            <font name="Lucida Grande" size="12">
              <color r="0" g="0" b="0" />
            </font>
          </style>
        </node>
        <node identifier="id-96c243cd" xsi:type="Label" x="201" y="1351" w="6318" h="884">
          <label xml:lang="en">Application Services Layer (operational)</label>
          <style>
            <fillColor r="210" g="215" b="215" a="100" />
            <lineColor r="92" g="92" b="92" a="100" />
            <font name="Lucida Grande" size="12">
              <color r="0" g="0" b="0" />
            </font>
          </style>
        </node>
        <node identifier="be1ffce4" xsi:type="Label" x="201" y="401" w="6318" h="884">
          <label xml:lang="en">Presentation Layer (User Interface)</label>
          <style>
            <fillColor r="210" g="215" b="215" a="100" />
            <lineColor r="92" g="92" b="92" a="100" />
            <font name="Lucida Grande" size="12">
              <color r="0" g="0" b="0" />
            </font>
          </style>
        </node>
        <node identifier="dc17353b" elementRef="id-3e1fe537" xsi:type="Element" x="3411" y="161" w="2222" h="4967">
          <style>
            <fillColor r="247" g="255" b="255" a="100" />
            <lineColor r="92" g="92" b="92" a="100" />
            <font name="Lucida Grande" size="12">
              <color r="255" g="0" b="0" />
            </font>
          </style>
          <node identifier="db18a4ab" elementRef="id-20dcbb18" xsi:type="Element" x="3491" y="4506" w="980" h="123">
            <style>
              <fillColor r="201" g="231" b="183" a="100" />
              <lineColor r="92" g="92" b="92" a="100" />
              <font name="Lucida Grande" size="12">
                <color r="0" g="0" b="0" />
              </font>
            </style>
          </node>
          <node identifier="ad4f789f" elementRef="id-037bfd41" xsi:type="Element" x="3596" y="676" w="588" h="514">
            <style>
              <fillColor r="255" g="255" b="255" a="100" />
              <lineColor r="92" g="92" b="92" a="100" />
              <font name="Lucida Grande" size="12">
                <color r="0" g="0" b="0" />
              </font>
            </style>
            <node identifier="id-3a9d0a2b" elementRef="id-44fcdd3d" xsi:type="Element" x="3706" y="731" w="322" h="430">
              <style>
                <fillColor r="181" g="255" b="255" a="100" />
                <lineColor r="92" g="92" b="92" a="100" />
                <font name="Lucida Grande" size="12">
                  <color r="0" g="0" b="0" />
                </font>
              </style>
              <node identifier="id-589fef8f" elementRef="id-9c970f90" xsi:type="Element" x="3726" y="781" w="290" h="360">
                <style>
                  <fillColor r="181" g="255" b="255" a="100" />
                  <lineColor r="92" g="92" b="92" a="100" />
                  <font name="Lucida Grande" size="12">
                    <color r="0" g="0" b="0" />
                  </font>
                </style>
                <node identifier="id-07c4fc66" elementRef="ba0b2aa0" xsi:type="Element" x="3746" y="836" w="261" h="55">
                  <style>
                    <fillColor r="181" g="255" b="255" a="100" />
                    <lineColor r="92" g="92" b="92" a="100" />
                    <font name="Lucida Grande" size="12">
                      <color r="0" g="0" b="0" />
                    </font>
                  </style>
                </node>
                <node identifier="cbc92354" elementRef="id-73f26451" xsi:type="Element" x="3746" y="901" w="261" h="55">
                  <style>
                    <fillColor r="181" g="255" b="255" a="100" />
                    <lineColor r="92" g="92" b="92" a="100" />
                    <font name="Lucida Grande" size="12">
                      <color r="0" g="0" b="0" />
                    </font>
                  </style>
                </node>
                <node identifier="d2ff1987" elementRef="id-551786c2" xsi:type="Element" x="3746" y="976" w="261" h="55">
                  <style>
                    <fillColor r="181" g="255" b="255" a="100" />
                    <lineColor r="92" g="92" b="92" a="100" />
                    <font name="Lucida Grande" size="12">
                      <color r="0" g="0" b="0" />
                    </font>
                  </style>
                </node>
                <node identifier="id-3c393b16" elementRef="id-32f7af32" xsi:type="Element" x="3752" y="1054" w="261" h="55">
                  <style>
                    <fillColor r="181" g="255" b="255" a="100" />
                    <lineColor r="92" g="92" b="92" a="100" />
                    <font name="Lucida Grande" size="12">
                      <color r="0" g="0" b="0" />
                    </font>
                  </style>
                </node>
              </node>
            </node>
          </node>
          <node identifier="id-209d0039" elementRef="c2aa831d" xsi:type="Element" x="4285" y="1321" w="420" h="1110">
            <style>
              <fillColor r="255" g="255" b="255" a="100" />
              <lineColor r="92" g="92" b="92" a="100" />
              <font name="Lucida Grande" size="12">
                <color r="0" g="0" b="0" />
              </font>
            </style>
            <node identifier="id-6c3cbd80" elementRef="id-59cb2834" xsi:type="Element" x="4310" y="1366" w="323" h="289">
              <style>
                <fillColor r="181" g="255" b="255" a="100" />
                <lineColor r="92" g="92" b="92" a="100" />
                <font name="Lucida Grande" size="12">
                  <color r="0" g="0" b="0" />
                </font>
              </style>
              <node identifier="f2944c9a" elementRef="id-4d2a8269" xsi:type="Element" x="4350" y="1501" w="271" h="111">
                <style>
                  <fillColor r="181" g="255" b="255" a="100" />
                  <lineColor r="92" g="92" b="92" a="100" />
                  <font name="Lucida Grande" size="12">
                    <color r="0" g="0" b="0" />
                  </font>
                </style>
                <node identifier="f7e8d10e" elementRef="f1b548a3" xsi:type="Element" x="4410" y="1541" w="136" h="55">
                  <style>
                    <fillColor r="181" g="255" b="255" a="100" />
                    <lineColor r="92" g="92" b="92" a="100" />
                    <font name="Lucida Grande" size="12">
                      <color r="0" g="0" b="0" />
                    </font>
                  </style>
                </node>
              </node>
              <node identifier="id-657a1a37" elementRef="d496da61" xsi:type="Element" x="4357" y="1419" w="120" h="55">
                <style>
                  <fillColor r="181" g="255" b="255" a="100" />
                  <lineColor r="92" g="92" b="92" a="100" />
                  <font name="Lucida Grande" size="12">
                    <color r="0" g="0" b="0" />
                  </font>
                </style>
              </node>
              <node identifier="b4e8c0b6" elementRef="id-12f32271" xsi:type="Element" x="4490" y="1417" w="120" h="55">
                <style>
                  <fillColor r="181" g="255" b="255" a="100" />
                  <lineColor r="92" g="92" b="92" a="100" />
                  <font name="Lucida Grande" size="12">
                    <color r="0" g="0" b="0" />
                  </font>
                </style>
              </node>
            </node>
          </node>
          <node identifier="id-113bd4f6" elementRef="aee8a19e" xsi:type="Element" x="4291" y="690" w="424" h="500">
            <style>
              <fillColor r="255" g="255" b="255" a="100" />
              <lineColor r="92" g="92" b="92" a="100" />
              <font name="Lucida Grande" size="12">
                <color r="0" g="0" b="0" />
              </font>
            </style>
            <node identifier="id-262b9db8" elementRef="id-05142199" xsi:type="Element" x="4326" y="975" w="322" h="171">
              <style>
                <fillColor r="181" g="255" b="255" a="100" />
                <lineColor r="92" g="92" b="92" a="100" />
                <font name="Lucida Grande" size="12">
                  <color r="0" g="0" b="0" />
                </font>
              </style>
              <node identifier="d2b7243f" elementRef="d6efe369" xsi:type="Element" x="4381" y="1025" w="240" h="110">
                <style>
                  <fillColor r="181" g="255" b="255" a="100" />
                  <lineColor r="92" g="92" b="92" a="100" />
                  <font name="Lucida Grande" size="12">
                    <color r="0" g="0" b="0" />
                  </font>
                </style>
                <node identifier="bdb3bde9" elementRef="a8ee8795" xsi:type="Element" x="4417" y="1081" w="161" h="55">
                  <style>
                    <fillColor r="181" g="255" b="255" a="100" />
                    <lineColor r="92" g="92" b="92" a="100" />
                    <font name="Lucida Grande" size="12">
                      <color r="0" g="0" b="0" />
                    </font>
                  </style>
                </node>
              </node>
            </node>
            <node identifier="id-05345794" elementRef="aab2e980" xsi:type="Element" x="4326" y="770" w="322" h="171">
              <style>
                <fillColor r="181" g="255" b="255" a="100" />
                <lineColor r="92" g="92" b="92" a="100" />
                <font name="Lucida Grande" size="12">
                  <color r="0" g="0" b="0" />
                </font>
              </style>
              <node identifier="id-8cfce524" elementRef="id-28fe1ee0" xsi:type="Element" x="4369" y="823" w="240" h="110">
                <style>
                  <fillColor r="181" g="255" b="255" a="100" />
                  <lineColor r="92" g="92" b="92" a="100" />
                  <font name="Lucida Grande" size="12">
                    <color r="0" g="0" b="0" />
                  </font>
                </style>
                <node identifier="id-1993dff3" elementRef="dac581b1" xsi:type="Element" x="4430" y="874" w="161" h="55">
                  <style>
                    <fillColor r="181" g="255" b="255" a="100" />
                    <lineColor r="92" g="92" b="92" a="100" />
                    <font name="Lucida Grande" size="12">
                      <color r="0" g="0" b="0" />
                    </font>
                  </style>
                </node>
              </node>
            </node>
          </node>
          <node identifier="id-71291aec" xsi:type="Label" x="4341" y="506" w="185" h="80">
            <label xml:lang="en">каталог</label>
            <style>
              <fillColor r="255" g="255" b="255" a="100" />
              <lineColor r="92" g="92" b="92" a="100" />
              <font name="Lucida Grande" size="12">
                <color r="0" g="0" b="0" />
              </font>
            </style>
          </node>
          <node identifier="id-095ff9a6" xsi:type="Label" x="3606" y="496" w="185" h="80">
            <label xml:lang="en">отдельно аккаунты</label>
            <style>
              <fillColor r="255" g="255" b="255" a="100" />
              <lineColor r="92" g="92" b="92" a="100" />
              <font name="Lucida Grande" size="12">
                <color r="0" g="0" b="0" />
              </font>
            </style>
          </node>
          <node identifier="e38f6286" elementRef="id-94446089" xsi:type="Element" x="3581" y="1321" w="652" h="1110">
            <style>
              <fillColor r="255" g="255" b="255" a="100" />
              <lineColor r="92" g="92" b="92" a="100" />
              <font name="Lucida Grande" size="12">
                <color r="0" g="0" b="0" />
              </font>
            </style>
            <node identifier="id-2b79e131" elementRef="fe880ef5" xsi:type="Element" x="3821" y="1366" w="380" h="441">
              <style>
                <fillColor r="181" g="255" b="255" a="100" />
                <lineColor r="92" g="92" b="92" a="100" />
                <font name="Lucida Grande" size="12">
                  <color r="0" g="0" b="0" />
                </font>
              </style>
              <node identifier="bfdc7ce3" elementRef="id-2c9bd0fb" xsi:type="Element" x="3836" y="1501" w="296" h="111">
                <style>
                  <fillColor r="181" g="255" b="255" a="100" />
                  <lineColor r="92" g="92" b="92" a="100" />
                  <font name="Lucida Grande" size="12">
                    <color r="0" g="0" b="0" />
                  </font>
                </style>
                <node identifier="c7959ee6" elementRef="a7f46b71" xsi:type="Element" x="3896" y="1541" w="136" h="55">
                  <style>
                    <fillColor r="181" g="255" b="255" a="100" />
                    <lineColor r="92" g="92" b="92" a="100" />
                    <font name="Lucida Grande" size="12">
                      <color r="0" g="0" b="0" />
                    </font>
                  </style>
                </node>
              </node>
              <node identifier="daebce29" elementRef="eb8e3d27" xsi:type="Element" x="3868" y="1419" w="120" h="55">
                <style>
                  <fillColor r="181" g="255" b="255" a="100" />
                  <lineColor r="92" g="92" b="92" a="100" />
                  <font name="Lucida Grande" size="12">
                    <color r="0" g="0" b="0" />
                  </font>
                </style>
              </node>
              <node identifier="a8226729" elementRef="id-63f0fb70" xsi:type="Element" x="4001" y="1417" w="120" h="55">
                <style>
                  <fillColor r="181" g="255" b="255" a="100" />
                  <lineColor r="92" g="92" b="92" a="100" />
                  <font name="Lucida Grande" size="12">
                    <color r="0" g="0" b="0" />
                  </font>
                </style>
              </node>
              <node identifier="id-6479e1dd" elementRef="id-073974d0" xsi:type="Element" x="3841" y="1656" w="296" h="111">
                <style>
                  <fillColor r="181" g="255" b="255" a="100" />
                  <lineColor r="92" g="92" b="92" a="100" />
                  <font name="Lucida Grande" size="12">
                    <color r="0" g="0" b="0" />
                  </font>
                </style>
                <node identifier="e802e1ff" elementRef="c69d7259" xsi:type="Element" x="3891" y="1701" w="210" h="55">
                  <style>
                    <fillColor r="181" g="255" b="255" a="100" />
                    <lineColor r="92" g="92" b="92" a="100" />
                    <font name="Lucida Grande" size="12">
                      <color r="0" g="0" b="0" />
                    </font>
                  </style>
                </node>
              </node>
            </node>
            <node identifier="id-66a1846d" elementRef="id-149de91a" xsi:type="Element" x="3646" y="1866" w="380" h="537">
              <style>
                <fillColor r="181" g="255" b="255" a="100" />
                <lineColor r="92" g="92" b="92" a="100" />
                <font name="Lucida Grande" size="12">
                  <color r="0" g="0" b="0" />
                </font>
              </style>
              <node identifier="be96bfb6" elementRef="a7fa4d9f" xsi:type="Element" x="3696" y="1912" w="120" h="55">
                <style>
                  <fillColor r="181" g="255" b="255" a="100" />
                  <lineColor r="92" g="92" b="92" a="100" />
                  <font name="Lucida Grande" size="12">
                    <color r="0" g="0" b="0" />
                  </font>
                </style>
              </node>
              <node identifier="f2046b05" elementRef="d2d5ff9b" xsi:type="Element" x="3674" y="1992" w="330" h="145">
                <style>
                  <fillColor r="181" g="255" b="255" a="100" />
                  <lineColor r="92" g="92" b="92" a="100" />
                  <font name="Lucida Grande" size="12">
                    <color r="0" g="0" b="0" />
                  </font>
                </style>
                <node identifier="id-71902e55" elementRef="id-4c5a15e8" xsi:type="Element" x="3729" y="2057" w="210" h="55">
                  <style>
                    <fillColor r="181" g="255" b="255" a="100" />
                    <lineColor r="92" g="92" b="92" a="100" />
                    <font name="Lucida Grande" size="12">
                      <color r="0" g="0" b="0" />
                    </font>
                  </style>
                </node>
              </node>
              <node identifier="id-26ca55f9" elementRef="id-42353705" xsi:type="Element" x="3674" y="2161" w="330" h="221">
                <style>
                  <fillColor r="181" g="255" b="255" a="100" />
                  <lineColor r="92" g="92" b="92" a="100" />
                  <font name="Lucida Grande" size="12">
                    <color r="0" g="0" b="0" />
                  </font>
                </style>
                <node identifier="b176f059" elementRef="id-1f3462e2" xsi:type="Element" x="3724" y="2232" w="120" h="55">
                  <style>
                    <fillColor r="181" g="255" b="255" a="100" />
                    <lineColor r="92" g="92" b="92" a="100" />
                    <font name="Lucida Grande" size="12">
                      <color r="0" g="0" b="0" />
                    </font>
                  </style>
                </node>
              </node>
            </node>
          </node>
          <node identifier="c5d604b6" elementRef="b8fb79cf" xsi:type="Element" x="3956" y="2976" w="174" h="191">
            <style>
              <fillColor r="181" g="255" b="255" a="100" />
              <lineColor r="92" g="92" b="92" a="100" />
              <font name="Lucida Grande" size="12">
                <color r="0" g="0" b="0" />
              </font>
            </style>
            <node identifier="id-27538f04" elementRef="id-8d892a42" xsi:type="Element" x="3986" y="3026" w="120" h="55">
              <style>
                <fillColor r="181" g="255" b="255" a="100" />
                <lineColor r="92" g="92" b="92" a="100" />
                <font name="Lucida Grande" size="12">
                  <color r="0" g="0" b="0" />
                </font>
              </style>
            </node>
            <node identifier="a31893ad" elementRef="f5027502" xsi:type="Element" x="3986" y="3091" w="120" h="55">
              <style>
                <fillColor r="181" g="255" b="255" a="100" />
                <lineColor r="92" g="92" b="92" a="100" />
                <font name="Lucida Grande" size="12">
                  <color r="0" g="0" b="0" />
                </font>
              </style>
            </node>
          </node>
          <node identifier="d70ad522" elementRef="id-75eaf240" xsi:type="Element" x="3516" y="2936" w="174" h="191">
            <style>
              <fillColor r="181" g="255" b="255" a="100" />
              <lineColor r="92" g="92" b="92" a="100" />
              <font name="Lucida Grande" size="12">
                <color r="0" g="0" b="0" />
              </font>
            </style>
            <node identifier="d73f1fa1" elementRef="id-764d4bcb" xsi:type="Element" x="3536" y="2986" w="120" h="55">
              <style>
                <fillColor r="181" g="255" b="255" a="100" />
                <lineColor r="92" g="92" b="92" a="100" />
                <font name="Lucida Grande" size="12">
                  <color r="0" g="0" b="0" />
                </font>
              </style>
            </node>
          </node>
          <node identifier="d15f8678" elementRef="c3059711" xsi:type="Element" x="3795" y="2736" w="189" h="185">
            <style>
              <fillColor r="181" g="255" b="255" a="100" />
              <lineColor r="92" g="92" b="92" a="100" />
              <font name="Lucida Grande" size="12">
                <color r="0" g="0" b="0" />
              </font>
            </style>
            <node identifier="id-1edd7c64" elementRef="id-0e0b4575" xsi:type="Element" x="3820" y="2766" w="120" h="55">
              <style>
                <fillColor r="181" g="255" b="255" a="100" />
                <lineColor r="92" g="92" b="92" a="100" />
                <font name="Lucida Grande" size="12">
                  <color r="0" g="0" b="0" />
                </font>
              </style>
            </node>
            <node identifier="id-139726df" elementRef="id-37cc4cf0" xsi:type="Element" x="3820" y="2831" w="120" h="55">
              <style>
                <fillColor r="181" g="255" b="255" a="100" />
                <lineColor r="92" g="92" b="92" a="100" />
                <font name="Lucida Grande" size="12">
                  <color r="0" g="0" b="0" />
                </font>
              </style>
            </node>
          </node>
          <node identifier="id-1542bd24" elementRef="id-3d07a689" xsi:type="Element" x="3771" y="4260" w="1518" h="106">
            <style>
              <fillColor r="201" g="231" b="183" a="100" />
              <lineColor r="92" g="92" b="92" a="100" />
              <font name="Lucida Grande" size="12">
                <color r="0" g="0" b="0" />
              </font>
            </style>
          </node>
          <node identifier="id-8e60c607" elementRef="id-75e6469b" xsi:type="Element" x="3746" y="3556" w="186" h="191">
            <style>
              <fillColor r="181" g="255" b="255" a="100" />
              <lineColor r="92" g="92" b="92" a="100" />
              <font name="Lucida Grande" size="12">
                <color r="0" g="0" b="0" />
              </font>
            </style>
            <node identifier="id-97dcebcc" elementRef="id-4efb44bb" xsi:type="Element" x="3786" y="3636" w="126" h="76">
              <style>
                <fillColor r="181" g="255" b="255" a="100" />
                <lineColor r="92" g="92" b="92" a="100" />
                <font name="Lucida Grande" size="12">
                  <color r="0" g="0" b="0" />
                </font>
              </style>
            </node>
          </node>
          <node identifier="id-1ca84a23" elementRef="id-3f490911" xsi:type="Element" x="4851" y="956" w="444" h="1480">
            <style>
              <fillColor r="255" g="255" b="255" a="100" />
              <lineColor r="92" g="92" b="92" a="100" />
              <font name="Lucida Grande" size="12">
                <color r="0" g="0" b="0" />
              </font>
            </style>
            <node identifier="id-702f9c96" elementRef="id-21fe1ef8" xsi:type="Element" x="4891" y="1012" w="276" h="135">
              <style>
                <fillColor r="181" g="255" b="255" a="100" />
                <lineColor r="92" g="92" b="92" a="100" />
                <font name="Lucida Grande" size="12">
                  <color r="0" g="0" b="0" />
                </font>
              </style>
              <node identifier="id-1756cc98" elementRef="ac9ccc41" xsi:type="Element" x="4925" y="1062" w="232" h="81">
                <style>
                  <fillColor r="181" g="255" b="255" a="100" />
                  <lineColor r="92" g="92" b="92" a="100" />
                  <font name="Lucida Grande" size="12">
                    <color r="0" g="0" b="0" />
                  </font>
                </style>
              </node>
            </node>
            <node identifier="id-8114c093" elementRef="id-06235a52" xsi:type="Element" x="4881" y="1351" w="366" h="351">
              <style>
                <fillColor r="181" g="255" b="255" a="100" />
                <lineColor r="92" g="92" b="92" a="100" />
                <font name="Lucida Grande" size="12">
                  <color r="0" g="0" b="0" />
                </font>
              </style>
              <node identifier="ce4d56cf" elementRef="id-9ac9c23e" xsi:type="Element" x="4937" y="1398" w="205" h="55">
                <style>
                  <fillColor r="181" g="255" b="255" a="100" />
                  <lineColor r="92" g="92" b="92" a="100" />
                  <font name="Lucida Grande" size="12">
                    <color r="0" g="0" b="0" />
                  </font>
                </style>
              </node>
              <node identifier="id-69e9a4f4" elementRef="be4d1b24" xsi:type="Element" x="4920" y="1496" w="302" h="161">
                <style>
                  <fillColor r="181" g="255" b="255" a="100" />
                  <lineColor r="92" g="92" b="92" a="100" />
                  <font name="Lucida Grande" size="12">
                    <color r="0" g="0" b="0" />
                  </font>
                </style>
                <node identifier="id-89098318" elementRef="d3693fe1" xsi:type="Element" x="4937" y="1552" w="120" h="55">
                  <style>
                    <fillColor r="181" g="255" b="255" a="100" />
                    <lineColor r="92" g="92" b="92" a="100" />
                    <font name="Lucida Grande" size="12">
                      <color r="0" g="0" b="0" />
                    </font>
                  </style>
                </node>
                <node identifier="id-74e0b67a" elementRef="id-9095d7ca" xsi:type="Element" x="5084" y="1556" w="120" h="55">
                  <style>
                    <fillColor r="181" g="255" b="255" a="100" />
                    <lineColor r="92" g="92" b="92" a="100" />
                    <font name="Lucida Grande" size="12">
                      <color r="0" g="0" b="0" />
                    </font>
                  </style>
                </node>
              </node>
            </node>
          </node>
          <node identifier="id-288cd891" xsi:type="Label" x="4891" y="556" w="185" h="80">
            <label xml:lang="en">ATOM</label>
            <style>
              <fillColor r="255" g="255" b="255" a="100" />
              <lineColor r="92" g="92" b="92" a="100" />
              <font name="Lucida Grande" size="12">
                <color r="0" g="0" b="0" />
              </font>
            </style>
          </node>
          <node identifier="id-8540ce18" elementRef="a33114ab" xsi:type="Element" x="4724" y="3584" w="376" h="204">
            <style>
              <fillColor r="181" g="255" b="255" a="100" />
              <lineColor r="92" g="92" b="92" a="100" />
              <font name="Lucida Grande" size="12">
                <color r="0" g="0" b="0" />
              </font>
            </style>
            <node identifier="e1b9bc4c" elementRef="id-45ca7810" xsi:type="Element" x="4814" y="3644" w="192" h="79">
              <style>
                <fillColor r="181" g="255" b="255" a="100" />
                <lineColor r="92" g="92" b="92" a="100" />
                <font name="Lucida Grande" size="12">
                  <color r="0" g="0" b="0" />
                </font>
              </style>
            </node>
          </node>
        </node>
        <node identifier="id-78456466" elementRef="id-46e885a0" xsi:type="Element" x="5660" y="161" w="837" h="4967">
          <style>
            <fillColor r="247" g="255" b="255" a="100" />
            <lineColor r="92" g="92" b="92" a="100" />
            <font name="Lucida Grande" size="12">
              <color r="255" g="0" b="0" />
            </font>
          </style>
        </node>
        <node identifier="ff850821" elementRef="bcc4903f" xsi:type="Element" x="851" y="161" w="880" h="4967">
          <style>
            <fillColor r="247" g="255" b="255" a="100" />
            <lineColor r="92" g="92" b="92" a="100" />
            <font name="Lucida Grande" size="12">
              <color r="255" g="0" b="0" />
            </font>
          </style>
          <node identifier="id-7fb70453" elementRef="c325a498" xsi:type="Element" x="969" y="4743" w="120" h="55">
            <style>
              <fillColor r="201" g="231" b="183" a="100" />
              <lineColor r="92" g="92" b="92" a="100" />
              <font name="Lucida Grande" size="12">
                <color r="0" g="0" b="0" />
              </font>
            </style>
          </node>
        </node>
        <node identifier="f354e1b1" elementRef="id-1e2e80cc" xsi:type="Element" x="1921" y="161" w="1436" h="4967">
          <style>
            <fillColor r="247" g="255" b="255" a="100" />
            <lineColor r="92" g="92" b="92" a="100" />
            <font name="Lucida Grande" size="12">
              <color r="255" g="0" b="0" />
            </font>
          </style>
          <node identifier="id-1aec3402" elementRef="id-5014ebdb" xsi:type="Element" x="2566" y="4501" w="596" h="123">
            <style>
              <fillColor r="201" g="231" b="183" a="100" />
              <lineColor r="92" g="92" b="92" a="100" />
              <font name="Lucida Grande" size="12">
                <color r="0" g="0" b="0" />
              </font>
            </style>
          </node>
          <node identifier="id-9fd10ae9" elementRef="id-821f3e6a" xsi:type="Element" x="1966" y="1361" w="616" h="1792">
            <style>
              <fillColor r="255" g="255" b="255" a="100" />
              <lineColor r="92" g="92" b="92" a="100" />
              <font name="Lucida Grande" size="12">
                <color r="0" g="0" b="0" />
              </font>
            </style>
          </node>
          <node identifier="c5942eb8" elementRef="f9b69534" xsi:type="Element" x="2716" y="1396" w="536" h="1736">
            <style>
              <fillColor r="255" g="255" b="255" a="100" />
              <lineColor r="92" g="92" b="92" a="100" />
              <font name="Lucida Grande" size="12">
                <color r="0" g="0" b="0" />
              </font>
            </style>
            <node identifier="id-92f6c8ac" elementRef="ca0a40a9" xsi:type="Element" x="2740" y="1524" w="476" h="455">
              <style>
                <fillColor r="181" g="255" b="255" a="100" />
                <lineColor r="92" g="92" b="92" a="100" />
                <font name="Lucida Grande" size="12">
                  <color r="0" g="0" b="0" />
                </font>
              </style>
              <node identifier="id-1ed6b08f" elementRef="id-4c2c51ec" xsi:type="Element" x="2815" y="1574" w="120" h="55">
                <style>
                  <fillColor r="181" g="255" b="255" a="100" />
                  <lineColor r="92" g="92" b="92" a="100" />
                  <font name="Lucida Grande" size="12">
                    <color r="0" g="0" b="0" />
                  </font>
                </style>
              </node>
              <node identifier="id-98dbb068" elementRef="cb05e122" xsi:type="Element" x="2960" y="1574" w="120" h="55">
                <style>
                  <fillColor r="181" g="255" b="255" a="100" />
                  <lineColor r="92" g="92" b="92" a="100" />
                  <font name="Lucida Grande" size="12">
                    <color r="0" g="0" b="0" />
                  </font>
                </style>
              </node>
              <node identifier="id-121012c2" elementRef="b93dd2ac" xsi:type="Element" x="2830" y="1644" w="300" h="146">
                <style>
                  <fillColor r="181" g="255" b="255" a="100" />
                  <lineColor r="92" g="92" b="92" a="100" />
                  <font name="Lucida Grande" size="12">
                    <color r="0" g="0" b="0" />
                  </font>
                </style>
                <node identifier="ae9b4743" elementRef="acdb4e5d" xsi:type="Element" x="2895" y="1674" w="170" h="100">
                  <style>
                    <fillColor r="181" g="255" b="255" a="100" />
                    <lineColor r="92" g="92" b="92" a="100" />
                    <font name="Lucida Grande" size="12">
                      <color r="0" g="0" b="0" />
                    </font>
                  </style>
                  <node identifier="be27df2e" elementRef="d4767110" xsi:type="Element" x="2920" y="1704" w="120" h="55">
                    <style>
                      <fillColor r="181" g="255" b="255" a="100" />
                      <lineColor r="92" g="92" b="92" a="100" />
                      <font name="Lucida Grande" size="12">
                        <color r="0" g="0" b="0" />
                      </font>
                    </style>
                  </node>
                </node>
              </node>
              <node identifier="b1820d7a" elementRef="id-9480a96a" xsi:type="Element" x="2829" y="1808" w="309" h="100">
                <style>
                  <fillColor r="181" g="255" b="255" a="100" />
                  <lineColor r="92" g="92" b="92" a="100" />
                  <font name="Lucida Grande" size="12">
                    <color r="0" g="0" b="0" />
                  </font>
                </style>
                <node identifier="id-366af3cd" elementRef="e8f50ee1" xsi:type="Element" x="2924" y="1838" w="120" h="55">
                  <style>
                    <fillColor r="181" g="255" b="255" a="100" />
                    <lineColor r="92" g="92" b="92" a="100" />
                    <font name="Lucida Grande" size="12">
                      <color r="0" g="0" b="0" />
                    </font>
                  </style>
                </node>
              </node>
            </node>
          </node>
          <node identifier="id-0adc2660" xsi:type="Label" x="2704" y="1232" w="185" h="80">
            <label xml:lang="en">pooling feeds</label>
            <style>
              <fillColor r="255" g="255" b="255" a="100" />
              <lineColor r="92" g="92" b="92" a="100" />
              <font name="Lucida Grande" size="12">
                <color r="0" g="0" b="0" />
              </font>
            </style>
          </node>
        </node>
        <node identifier="id-2fa0b694" elementRef="id-9fdc1d3c" xsi:type="Element" x="3426" y="5311" w="880" h="140">
          <style>
            <fillColor r="247" g="255" b="255" a="100" />
            <lineColor r="92" g="92" b="92" a="100" />
            <font name="Lucida Grande" size="12">
              <color r="0" g="0" b="0" />
            </font>
          </style>
        </node>
        <node identifier="d5d04209" elementRef="id-9e77e08a" xsi:type="Element" x="5716" y="5321" w="880" h="140">
          <style>
            <fillColor r="247" g="255" b="255" a="100" />
            <lineColor r="92" g="92" b="92" a="100" />
            <font name="Lucida Grande" size="12">
              <color r="0" g="0" b="0" />
            </font>
          </style>
        </node>
        <node identifier="id-7b68939c" xsi:type="Label" x="208" y="5621" w="6084" h="140">
          <label xml:lang="en">Infrаstrсtиrе Layer</label>
          <style>
            <fillColor r="210" g="215" b="215" a="100" />
            <lineColor r="92" g="92" b="92" a="100" />
            <font name="Lucida Grande" size="12">
              <color r="0" g="0" b="0" />
            </font>
          </style>
        </node>
        <node identifier="c2e86608" elementRef="b37b5820" xsi:type="Element" x="386" y="5556" w="5831" h="256">
          <style>
            <fillColor r="247" g="255" b="255" a="100" />
            <lineColor r="92" g="92" b="92" a="100" />
            <font name="Lucida Grande" size="12">
              <color r="0" g="0" b="0" />
            </font>
          </style>
          <node identifier="d761e0fb" elementRef="d0d4b84b" xsi:type="Element" x="531" y="5665" w="5576" h="71">
            <style>
              <fillColor r="201" g="231" b="183" a="100" />
              <lineColor r="92" g="92" b="92" a="100" />
              <font name="Lucida Grande" size="12">
                <color r="0" g="0" b="0" />
              </font>
            </style>
          </node>
        </node>
        <connection identifier="id-48af48c5" relationshipRef="bc599d4c" xsi:type="Relationship" source="db18a4ab" target="d761e0fb">
          <style>
            <lineColor r="0" g="0" b="0" />
            <font name="Lucida Grande" size="12">
              <color r="0" g="0" b="0" />
            </font>
          </style>
        </connection>
        <connection identifier="ffa26226" relationshipRef="id-99a86104" xsi:type="Relationship" source="db18a4ab" target="id-6c3cbd80">
          <style>
            <lineColor r="0" g="0" b="0" />
            <font name="Lucida Grande" size="12">
              <color r="0" g="0" b="0" />
            </font>
          </style>
        </connection>
        <connection identifier="f3eb77cb" relationshipRef="af661ec4" xsi:type="Relationship" source="db18a4ab" target="id-6479e1dd">
          <style>
            <lineColor r="0" g="0" b="0" />
            <font name="Lucida Grande" size="12">
              <color r="0" g="0" b="0" />
            </font>
          </style>
        </connection>
        <connection identifier="ab5a586f" relationshipRef="id-73d63986" xsi:type="Relationship" source="f3eb77cb" target="c5d604b6">
          <style>
            <lineColor r="192" g="192" b="192" />
            <font name="Lucida Grande" size="12">
              <color r="0" g="0" b="0" />
            </font>
          </style>
        </connection>
        <connection identifier="id-5d7a87cf" relationshipRef="id-8c441cb0" xsi:type="Relationship" source="db18a4ab" target="bfdc7ce3">
          <style>
            <lineColor r="0" g="0" b="0" />
            <font name="Lucida Grande" size="12">
              <color r="0" g="0" b="0" />
            </font>
          </style>
          <bendpoint x="4143" y="1557" />
        </connection>
        <connection identifier="id-7153b95f" relationshipRef="id-2c47024d" xsi:type="Relationship" source="db18a4ab" target="f2046b05">
          <style>
            <lineColor r="0" g="0" b="0" />
            <font name="Lucida Grande" size="12">
              <color r="0" g="0" b="0" />
            </font>
          </style>
          <bendpoint x="3702" y="3313" />
        </connection>
        <connection identifier="id-2ea93bac" relationshipRef="id-38e94c01" xsi:type="Relationship" source="db18a4ab" target="id-26ca55f9">
          <style>
            <lineColor r="0" g="0" b="0" />
            <font name="Lucida Grande" size="12">
              <color r="0" g="0" b="0" />
            </font>
          </style>
          <bendpoint x="3722" y="3451" />
        </connection>
        <connection identifier="id-6dcc3a12" relationshipRef="f49eba3b" xsi:type="Relationship" source="id-07c4fc66" target="bfdc7ce3">
          <style>
            <lineColor r="0" g="0" b="0" />
            <font name="Lucida Grande" size="12">
              <color r="0" g="0" b="0" />
            </font>
          </style>
          <bendpoint x="3860" y="1194" />
        </connection>
        <connection identifier="f28bc5d8" relationshipRef="id-63c9fb11" xsi:type="Relationship" source="cbc92354" target="id-6479e1dd">
          <style>
            <lineColor r="0" g="0" b="0" />
            <font name="Lucida Grande" size="12">
              <color r="0" g="0" b="0" />
            </font>
          </style>
          <bendpoint x="3840" y="1304" />
        </connection>
        <connection identifier="id-04508f5b" relationshipRef="d0027bbf" xsi:type="Relationship" source="id-3c393b16" target="id-66a1846d">
          <style>
            <lineColor r="0" g="0" b="0" />
            <font name="Lucida Grande" size="12">
              <color r="0" g="0" b="0" />
            </font>
          </style>
          <bendpoint x="3754" y="1484" />
        </connection>
        <connection identifier="cb1b083a" relationshipRef="id-21d9fd04" xsi:type="Relationship" source="f7e8d10e" target="id-657a1a37">
          <style>
            <lineColor r="0" g="0" b="0" />
            <font name="Lucida Grande" size="12">
              <color r="0" g="0" b="0" />
            </font>
          </style>
        </connection>
        <connection identifier="id-08974cda" relationshipRef="id-559be726" xsi:type="Relationship" source="f7e8d10e" target="b4e8c0b6">
          <style>
            <lineColor r="0" g="0" b="0" />
            <font name="Lucida Grande" size="12">
              <color r="0" g="0" b="0" />
            </font>
          </style>
        </connection>
        <connection identifier="id-7f3b87a4" relationshipRef="fb6e111d" xsi:type="Relationship" source="bdb3bde9" target="f2944c9a">
          <style>
            <lineColor r="0" g="0" b="0" />
            <font name="Lucida Grande" size="12">
              <color r="0" g="0" b="0" />
            </font>
          </style>
          <bendpoint x="4570" y="1325" />
        </connection>
        <connection identifier="ea3a1315" relationshipRef="id-4be83721" xsi:type="Relationship" source="c7959ee6" target="a8226729">
          <style>
            <lineColor r="0" g="0" b="0" />
            <font name="Lucida Grande" size="12">
              <color r="0" g="0" b="0" />
            </font>
          </style>
        </connection>
        <connection identifier="id-5d97b31e" relationshipRef="id-14ebad19" xsi:type="Relationship" source="c7959ee6" target="daebce29">
          <style>
            <lineColor r="0" g="0" b="0" />
            <font name="Lucida Grande" size="12">
              <color r="0" g="0" b="0" />
            </font>
          </style>
        </connection>
        <connection identifier="id-1c773929" relationshipRef="a4d722a2" xsi:type="Relationship" source="e802e1ff" target="a8226729">
          <style>
            <lineColor r="0" g="0" b="0" />
            <font name="Lucida Grande" size="12">
              <color r="0" g="0" b="0" />
            </font>
          </style>
        </connection>
        <connection identifier="da6c021c" relationshipRef="id-04a3dac7" xsi:type="Relationship" source="id-71902e55" target="be96bfb6">
          <style>
            <lineColor r="0" g="0" b="0" />
            <font name="Lucida Grande" size="12">
              <color r="0" g="0" b="0" />
            </font>
          </style>
        </connection>
        <connection identifier="id-173d80b9" relationshipRef="id-4a7ad951" xsi:type="Relationship" source="b176f059" target="id-97dcebcc">
          <style>
            <lineColor r="0" g="0" b="0" />
            <font name="Lucida Grande" size="12">
              <color r="0" g="0" b="0" />
            </font>
          </style>
        </connection>
        <connection identifier="id-9db81cd5" relationshipRef="d1ac6f63" xsi:type="Relationship" source="d70ad522" target="id-7153b95f">
          <style>
            <lineColor r="192" g="192" b="192" />
            <font name="Lucida Grande" size="12">
              <color r="0" g="0" b="0" />
            </font>
          </style>
        </connection>
        <connection identifier="id-5f81f288" relationshipRef="f6afe33d" xsi:type="Relationship" source="d15f8678" target="id-173d80b9">
          <style>
            <lineColor r="192" g="192" b="192" />
            <font name="Lucida Grande" size="12">
              <color r="0" g="0" b="0" />
            </font>
          </style>
        </connection>
        <connection identifier="ae8ce49b" relationshipRef="id-3701b1fa" xsi:type="Relationship" source="id-8e60c607" target="id-1542bd24">
          <style>
            <lineColor r="0" g="0" b="0" />
            <font name="Lucida Grande" size="12">
              <color r="0" g="0" b="0" />
            </font>
          </style>
        </connection>
        <connection identifier="a073e3a0" relationshipRef="fc4029e2" xsi:type="Relationship" source="id-1756cc98" target="id-69e9a4f4">
          <style>
            <lineColor r="0" g="0" b="0" />
            <font name="Lucida Grande" size="12">
              <color r="0" g="0" b="0" />
            </font>
          </style>
        </connection>
        <connection identifier="c4b2fddc" relationshipRef="id-6be3a7db" xsi:type="Relationship" source="id-89098318" target="e1b9bc4c">
          <style>
            <lineColor r="0" g="0" b="0" />
            <font name="Lucida Grande" size="12">
              <color r="0" g="0" b="0" />
            </font>
          </style>
        </connection>
        <connection identifier="id-362e7c51" relationshipRef="id-6f4563da" xsi:type="Relationship" source="id-74e0b67a" target="ce4d56cf">
          <style>
            <lineColor r="0" g="0" b="0" />
            <font name="Lucida Grande" size="12">
              <color r="0" g="0" b="0" />
            </font>
          </style>
        </connection>
        <connection identifier="id-7c00f735" relationshipRef="id-5cea3d2c" xsi:type="Relationship" source="id-8540ce18" target="id-1542bd24">
          <style>
            <lineColor r="0" g="0" b="0" />
            <font name="Lucida Grande" size="12">
              <color r="0" g="0" b="0" />
            </font>
          </style>
        </connection>
        <connection identifier="d30b7c75" relationshipRef="id-19952c51" xsi:type="Relationship" source="id-7fb70453" target="d761e0fb">
          <style>
            <lineColor r="0" g="0" b="0" />
            <font name="Lucida Grande" size="12">
              <color r="0" g="0" b="0" />
            </font>
          </style>
        </connection>
        <connection identifier="id-108a83aa" relationshipRef="id-0aa8d98c" xsi:type="Relationship" source="id-1aec3402" target="d761e0fb">
          <style>
            <lineColor r="0" g="0" b="0" />
            <font name="Lucida Grande" size="12">
              <color r="0" g="0" b="0" />
            </font>
          </style>
        </connection>
        <connection identifier="ef390402" relationshipRef="c7546626" xsi:type="Relationship" source="be27df2e" target="b1820d7a">
          <style>
            <lineColor r="0" g="0" b="0" />
            <font name="Lucida Grande" size="12">
              <color r="0" g="0" b="0" />
            </font>
          </style>
        </connection>
        <connection identifier="id-28a0e746" relationshipRef="id-6e6f07b6" xsi:type="Relationship" source="b1820d7a" target="id-1ed6b08f">
          <style>
            <lineColor r="0" g="0" b="0" />
            <font name="Lucida Grande" size="12">
              <color r="0" g="0" b="0" />
            </font>
          </style>
        </connection>
        <connection identifier="id-3ca68cec" relationshipRef="id-2867a96f" xsi:type="Relationship" source="id-366af3cd" target="id-1aec3402">
          <style>
            <lineColor r="0" g="0" b="0" />
            <font name="Lucida Grande" size="12">
              <color r="0" g="0" b="0" />
            </font>
          </style>
        </connection>
      </view>
    </diagrams>
  </views>
</model>
