<?xml version="1.0" encoding="UTF-8"?>
<model xmlns="http://www.opengroup.org/xsd/archimate/3.0/" xmlns:xsi="http://www.w3.org/2001/XMLSchema-instance" xsi:schemaLocation="http://www.opengroup.org/xsd/archimate/3.0/ http://www.opengroup.org/xsd/archimate/3.1/archimate3_Diagram.xsd" identifier="id-74e30801">
  <name xml:lang="en">4 specification</name>
  <elements>
    <element identifier="d881849b" xsi:type="BusinessObject">
      <name xml:lang="en">entity 1</name>
    </element>
    <element identifier="id-20409df4" xsi:type="BusinessObject">
      <name xml:lang="en">entity 1</name>
    </element>
    <element identifier="id-8d9bbaca" xsi:type="ApplicationComponent">
      <name xml:lang="en">class 1</name>
      <documentation xml:lang="en">Предикаты - это&#xD;
функции, выдающие значения "истина" или "ложь", которые можно комбинировать&#xD;
с помощью таких операций, как И и или для выражения более сложных правил.</documentation>
    </element>
    <element identifier="bac230a8" xsi:type="ApplicationFunction">
      <name xml:lang="en">some rule</name>
    </element>
    <element identifier="id-0f89bc46" xsi:type="ApplicationComponent">
      <name xml:lang="en">class 1</name>
    </element>
    <element identifier="id-5812a8e9" xsi:type="DataObject">
      <name xml:lang="en">id</name>
    </element>
    <element identifier="a1218ba9" xsi:type="ApplicationFunction">
      <name xml:lang="en">Identify the identity with (object)</name>
    </element>
    <element identifier="id-004a90d8" xsi:type="ApplicationComponent">
      <name xml:lang="en">value type 1</name>
      <documentation xml:lang="en">СПЕЦИФИКАЦИЯ - это предикат, который определяет, удовлетворяет объект некоторым критериям или нет.&#xD;
&#xD;
СПЕIИФИКАЦИЯ (SPECIFICATION) задает условие-ограничение на состояние другого объекта, которое может возникнуть, а может и не возникнуть.</documentation>
    </element>
    <element identifier="id-3dea59ff" xsi:type="ApplicationFunction">
      <name xml:lang="en">test (object of class 1)</name>
      <documentation xml:lang="en">СПЕЦИФИКАЦИЯ может проверять любой объект на соответствие заданным критериям.</documentation>
    </element>
    <element identifier="id-33fe7f23" xsi:type="ApplicationProcess">
      <name xml:lang="en">return bool</name>
    </element>
    <element identifier="id-2823d98b" xsi:type="ApplicationInterface">
      <name xml:lang="en">specification</name>
    </element>
    <element identifier="id-92547df5" xsi:type="ApplicationFunction">
      <name xml:lang="en">test (any object)</name>
      <documentation xml:lang="en">СПЕЦИФИКАЦИЯ может проверять любой объект на соответствие заданным критериям.</documentation>
    </element>
    <element identifier="a36f1e07" xsi:type="ApplicationProcess">
      <name xml:lang="en">return bool</name>
    </element>
    <element identifier="id-9e98c348" xsi:type="ApplicationFunction">
      <name xml:lang="en">and (specification)</name>
    </element>
    <element identifier="c2eed3bc" xsi:type="ApplicationFunction">
      <name xml:lang="en">or (specification)</name>
    </element>
    <element identifier="id-8cdcc1b4" xsi:type="ApplicationProcess">
      <name xml:lang="en">return new specification</name>
    </element>
    <element identifier="id-92225d5c" xsi:type="ApplicationProcess">
      <name xml:lang="en">return new specification</name>
    </element>
    <element identifier="id-560e33c6" xsi:type="ApplicationFunction">
      <name xml:lang="en">not ()</name>
    </element>
    <element identifier="id-81d157cb" xsi:type="ApplicationProcess">
      <name xml:lang="en">return new specification</name>
    </element>
    <element identifier="ebafa7b7" xsi:type="Constraint">
      <name xml:lang="en">Constraint 1</name>
    </element>
    <element identifier="id-91aa2bab" xsi:type="Requirement">
      <name xml:lang="en">Identifier unchanged for the object</name>
    </element>
    <element identifier="id-220dec2b" xsi:type="Requirement">
      <name xml:lang="en">unique value within the system</name>
    </element>
  </elements>
  <relationships>
    <relationship identifier="id-26d4c73a" source="d881849b" target="ebafa7b7" xsi:type="Association" />
    <relationship identifier="id-29f59532" source="id-220dec2b" target="id-5812a8e9" xsi:type="Association" />
    <relationship identifier="fe5ef6d3" source="id-0f89bc46" target="id-5812a8e9" xsi:type="Access" accessType="Write" />
    <relationship identifier="id-29cd4ce9" source="a1218ba9" target="id-5812a8e9" xsi:type="Access" accessType="Write" />
    <relationship identifier="f8869861" source="id-5812a8e9" target="id-91aa2bab" xsi:type="Association" />
    <relationship identifier="e8b84b4d" source="id-0f89bc46" target="id-20409df4" xsi:type="Association" />
    <relationship identifier="id-61f21284" source="id-0f89bc46" target="a1218ba9" xsi:type="Assignment" />
    <relationship identifier="id-82c53462" source="id-3dea59ff" target="id-33fe7f23" xsi:type="Composition" />
    <relationship identifier="id-906f984f" source="id-004a90d8" target="id-3dea59ff" xsi:type="Assignment" />
    <relationship identifier="id-57e50452" source="id-3dea59ff" target="id-8d9bbaca" xsi:type="Flow" />
    <relationship identifier="bf382ca7" source="id-8d9bbaca" target="d881849b" xsi:type="Association" />
    <relationship identifier="dfc29844" source="ebafa7b7" target="id-004a90d8" xsi:type="Association" />
    <relationship identifier="id-39181947" source="id-004a90d8" target="id-2823d98b" xsi:type="Realization" />
    <relationship identifier="id-18cfe0fe" source="id-92547df5" target="a36f1e07" xsi:type="Composition" />
    <relationship identifier="id-789caea8" source="id-9e98c348" target="id-8cdcc1b4" xsi:type="Composition" />
    <relationship identifier="b997055d" source="c2eed3bc" target="id-92225d5c" xsi:type="Composition" />
    <relationship identifier="id-831c1af1" source="id-560e33c6" target="id-81d157cb" xsi:type="Composition" />
  </relationships>
  <organizations>
    <item>
      <label xml:lang="en">Business</label>
      <item identifierRef="d881849b" />
      <item identifierRef="id-20409df4" />
    </item>
    <item>
      <label xml:lang="en">Application</label>
      <item identifierRef="id-8d9bbaca" />
      <item identifierRef="bac230a8" />
      <item identifierRef="id-0f89bc46" />
      <item identifierRef="id-5812a8e9" />
      <item identifierRef="a1218ba9" />
      <item identifierRef="id-004a90d8" />
      <item identifierRef="id-3dea59ff" />
      <item identifierRef="id-33fe7f23" />
      <item identifierRef="id-2823d98b" />
      <item identifierRef="id-92547df5" />
      <item identifierRef="a36f1e07" />
      <item identifierRef="id-9e98c348" />
      <item identifierRef="c2eed3bc" />
      <item identifierRef="id-8cdcc1b4" />
      <item identifierRef="id-92225d5c" />
      <item identifierRef="id-560e33c6" />
      <item identifierRef="id-81d157cb" />
    </item>
    <item>
      <label xml:lang="en">Motivation</label>
      <item identifierRef="ebafa7b7" />
      <item identifierRef="id-91aa2bab" />
      <item identifierRef="id-220dec2b" />
    </item>
    <item>
      <label xml:lang="en">Relations</label>
      <item identifierRef="id-26d4c73a" />
      <item identifierRef="id-29f59532" />
      <item identifierRef="fe5ef6d3" />
      <item identifierRef="id-29cd4ce9" />
      <item identifierRef="f8869861" />
      <item identifierRef="e8b84b4d" />
      <item identifierRef="id-61f21284" />
      <item identifierRef="id-82c53462" />
      <item identifierRef="id-906f984f" />
      <item identifierRef="id-57e50452" />
      <item identifierRef="bf382ca7" />
      <item identifierRef="dfc29844" />
      <item identifierRef="id-39181947" />
      <item identifierRef="id-18cfe0fe" />
      <item identifierRef="id-789caea8" />
      <item identifierRef="b997055d" />
      <item identifierRef="id-831c1af1" />
    </item>
    <item>
      <label xml:lang="en">Views</label>
      <item identifierRef="ec851206" />
      <item identifierRef="id-9f1d36c3" />
    </item>
  </organizations>
  <views>
    <diagrams>
      <view identifier="ec851206" xsi:type="Diagram">
        <name xml:lang="en">specification</name>
        <node identifier="id-193eac85" x="190" y="495" w="766" h="334" xsi:type="Container">
          <label xml:lang="en">Domain model (information systems: application layer)</label>
          <style>
            <fillColor r="210" g="215" b="215" a="100" />
            <lineColor r="92" g="92" b="92" a="100" />
            <font name="Lucida Grande" size="12">
              <color r="0" g="0" b="0" />
            </font>
          </style>
          <node identifier="d5c611a5" elementRef="id-8d9bbaca" xsi:type="Element" x="256" y="595" w="239" h="160">
            <style>
              <fillColor r="181" g="255" b="255" a="100" />
              <lineColor r="92" g="92" b="92" a="100" />
              <font name="Lucida Grande" size="12">
                <color r="0" g="0" b="0" />
              </font>
            </style>
          </node>
          <node identifier="cdc0f382" elementRef="id-004a90d8" xsi:type="Element" x="660" y="595" w="239" h="160">
            <style>
              <fillColor r="181" g="255" b="255" a="100" />
              <lineColor r="92" g="92" b="92" a="100" />
              <font name="Lucida Grande" size="12">
                <color r="0" g="0" b="0" />
              </font>
            </style>
            <node identifier="id-68991dc4" elementRef="id-3dea59ff" xsi:type="Element" x="700" y="640" w="186" h="96">
              <style>
                <fillColor r="181" g="255" b="255" a="100" />
                <lineColor r="92" g="92" b="92" a="100" />
                <font name="Lucida Grande" size="12">
                  <color r="0" g="0" b="0" />
                </font>
              </style>
              <node identifier="id-27ac1ce8" elementRef="id-33fe7f23" xsi:type="Element" x="745" y="680" w="120" h="55">
                <style>
                  <fillColor r="181" g="255" b="255" a="100" />
                  <lineColor r="92" g="92" b="92" a="100" />
                  <font name="Lucida Grande" size="12">
                    <color r="0" g="0" b="0" />
                  </font>
                </style>
              </node>
            </node>
          </node>
          <node identifier="af57ed93" xsi:type="Label" x="565" y="540" w="297" h="60">
            <label xml:lang="en">This type is called a specification&#xD;
The method tests satisfaction with some constraint</label>
            <style>
              <fillColor r="255" g="255" b="255" a="100" />
              <lineColor r="92" g="92" b="92" a="100" />
              <font name="Lucida Grande" size="12">
                <color r="255" g="0" b="0" />
              </font>
            </style>
          </node>
        </node>
        <node identifier="id-6e9df1cf" x="190" y="120" w="766" h="334" xsi:type="Container">
          <label xml:lang="en">Conceptual domain model (business layer)</label>
          <style>
            <fillColor r="210" g="215" b="215" a="100" />
            <lineColor r="92" g="92" b="92" a="100" />
            <font name="Lucida Grande" size="12">
              <color r="0" g="0" b="0" />
            </font>
          </style>
          <node identifier="id-55cb72a1" elementRef="d881849b" xsi:type="Element" x="246" y="208" w="239" h="160">
            <style>
              <fillColor r="255" g="255" b="181" a="100" />
              <lineColor r="92" g="92" b="92" a="100" />
              <font name="Lucida Grande" size="12">
                <color r="0" g="0" b="0" />
              </font>
            </style>
          </node>
          <node identifier="id-3daf97c5" elementRef="ebafa7b7" xsi:type="Element" x="645" y="210" w="239" h="160">
            <style>
              <fillColor r="204" g="204" b="255" a="100" />
              <lineColor r="92" g="92" b="92" a="100" />
              <font name="Lucida Grande" size="12">
                <color r="0" g="0" b="0" />
              </font>
            </style>
          </node>
        </node>
        <connection identifier="id-9160878c" relationshipRef="bf382ca7" xsi:type="Relationship" source="d5c611a5" target="id-55cb72a1">
          <style>
            <lineColor r="192" g="192" b="192" />
            <font name="Lucida Grande" size="12">
              <color r="0" g="0" b="0" />
            </font>
          </style>
        </connection>
        <connection identifier="d089ea36" relationshipRef="id-57e50452" xsi:type="Relationship" source="id-68991dc4" target="d5c611a5">
          <style>
            <lineColor r="0" g="0" b="0" />
            <font name="Lucida Grande" size="12">
              <color r="0" g="0" b="0" />
            </font>
          </style>
        </connection>
        <connection identifier="id-879fb380" relationshipRef="id-26d4c73a" xsi:type="Relationship" source="id-55cb72a1" target="id-3daf97c5">
          <style>
            <lineColor r="0" g="0" b="0" />
            <font name="Lucida Grande" size="12">
              <color r="0" g="0" b="0" />
            </font>
          </style>
        </connection>
        <connection identifier="id-540ec210" relationshipRef="dfc29844" xsi:type="Relationship" source="id-3daf97c5" target="cdc0f382">
          <style>
            <lineColor r="192" g="192" b="192" />
            <font name="Lucida Grande" size="12">
              <color r="0" g="0" b="0" />
            </font>
          </style>
        </connection>
      </view>
      <view identifier="id-9f1d36c3" xsi:type="Diagram">
        <name xml:lang="en">abstract specification</name>
        <node identifier="id-416acc12" x="190" y="130" w="766" h="843" xsi:type="Container">
          <label xml:lang="en">Domain model (information systems: application layer)</label>
          <style>
            <fillColor r="210" g="215" b="215" a="100" />
            <lineColor r="92" g="92" b="92" a="100" />
            <font name="Lucida Grande" size="12">
              <color r="0" g="0" b="0" />
            </font>
          </style>
          <node identifier="id-0a37e8ef" elementRef="id-004a90d8" xsi:type="Element" x="430" y="745" w="239" h="160">
            <style>
              <fillColor r="181" g="255" b="255" a="100" />
              <lineColor r="92" g="92" b="92" a="100" />
              <font name="Lucida Grande" size="12">
                <color r="0" g="0" b="0" />
              </font>
            </style>
            <node identifier="id-4085e38e" elementRef="id-3dea59ff" xsi:type="Element" x="490" y="790" w="166" h="96">
              <style>
                <fillColor r="181" g="255" b="255" a="100" />
                <lineColor r="92" g="92" b="92" a="100" />
                <font name="Lucida Grande" size="12">
                  <color r="0" g="0" b="0" />
                </font>
              </style>
              <node identifier="id-38acae0f" elementRef="id-33fe7f23" xsi:type="Element" x="535" y="830" w="120" h="55">
                <style>
                  <fillColor r="181" g="255" b="255" a="100" />
                  <lineColor r="92" g="92" b="92" a="100" />
                  <font name="Lucida Grande" size="12">
                    <color r="0" g="0" b="0" />
                  </font>
                </style>
              </node>
            </node>
          </node>
          <node identifier="e7ca3661" elementRef="id-2823d98b" xsi:type="Element" x="430" y="190" w="245" h="505">
            <style>
              <fillColor r="181" g="255" b="255" a="100" />
              <lineColor r="92" g="92" b="92" a="100" />
              <font name="Lucida Grande" size="12">
                <color r="0" g="0" b="0" />
              </font>
            </style>
            <node identifier="id-2804cf2c" elementRef="id-92547df5" xsi:type="Element" x="495" y="250" w="166" h="96">
              <style>
                <fillColor r="181" g="255" b="255" a="100" />
                <lineColor r="92" g="92" b="92" a="100" />
                <font name="Lucida Grande" size="12">
                  <color r="0" g="0" b="0" />
                </font>
              </style>
              <node identifier="id-45f75442" elementRef="a36f1e07" xsi:type="Element" x="540" y="290" w="120" h="55">
                <style>
                  <fillColor r="181" g="255" b="255" a="100" />
                  <lineColor r="92" g="92" b="92" a="100" />
                  <font name="Lucida Grande" size="12">
                    <color r="0" g="0" b="0" />
                  </font>
                </style>
              </node>
            </node>
            <node identifier="id-41b1a79e" elementRef="id-9e98c348" xsi:type="Element" x="495" y="360" w="166" h="96">
              <style>
                <fillColor r="181" g="255" b="255" a="100" />
                <lineColor r="92" g="92" b="92" a="100" />
                <font name="Lucida Grande" size="12">
                  <color r="0" g="0" b="0" />
                </font>
              </style>
              <node identifier="id-28645598" elementRef="id-8cdcc1b4" xsi:type="Element" x="540" y="400" w="120" h="55">
                <style>
                  <fillColor r="181" g="255" b="255" a="100" />
                  <lineColor r="92" g="92" b="92" a="100" />
                  <font name="Lucida Grande" size="12">
                    <color r="0" g="0" b="0" />
                  </font>
                </style>
              </node>
            </node>
            <node identifier="id-88ba9d3d" elementRef="c2eed3bc" xsi:type="Element" x="495" y="474" w="166" h="96">
              <style>
                <fillColor r="181" g="255" b="255" a="100" />
                <lineColor r="92" g="92" b="92" a="100" />
                <font name="Lucida Grande" size="12">
                  <color r="0" g="0" b="0" />
                </font>
              </style>
              <node identifier="d88e92a8" elementRef="id-92225d5c" xsi:type="Element" x="540" y="514" w="120" h="55">
                <style>
                  <fillColor r="181" g="255" b="255" a="100" />
                  <lineColor r="92" g="92" b="92" a="100" />
                  <font name="Lucida Grande" size="12">
                    <color r="0" g="0" b="0" />
                  </font>
                </style>
              </node>
            </node>
            <node identifier="c356b858" elementRef="id-560e33c6" xsi:type="Element" x="495" y="585" w="166" h="96">
              <style>
                <fillColor r="181" g="255" b="255" a="100" />
                <lineColor r="92" g="92" b="92" a="100" />
                <font name="Lucida Grande" size="12">
                  <color r="0" g="0" b="0" />
                </font>
              </style>
              <node identifier="id-27f09128" elementRef="id-81d157cb" xsi:type="Element" x="540" y="625" w="120" h="55">
                <style>
                  <fillColor r="181" g="255" b="255" a="100" />
                  <lineColor r="92" g="92" b="92" a="100" />
                  <font name="Lucida Grande" size="12">
                    <color r="0" g="0" b="0" />
                  </font>
                </style>
              </node>
            </node>
          </node>
          <node identifier="id-315edfd2" xsi:type="Label" x="655" y="365" w="237" h="305">
            <label xml:lang="en">Methods create a new specification, which is a combination of two.&#xD;
Such methods allow you to build complex specifications.</label>
            <style>
              <fillColor r="255" g="255" b="255" a="100" />
              <lineColor r="92" g="92" b="92" a="100" />
              <font name="Lucida Grande" size="12">
                <color r="255" g="0" b="0" />
              </font>
            </style>
          </node>
        </node>
        <connection identifier="id-4d16c195" relationshipRef="id-39181947" xsi:type="Relationship" source="id-0a37e8ef" target="e7ca3661">
          <style>
            <lineColor r="0" g="0" b="0" />
            <font name="Lucida Grande" size="12">
              <color r="0" g="0" b="0" />
            </font>
          </style>
        </connection>
      </view>
    </diagrams>
  </views>
</model>
